[
    {
        "label": "background",
        "xmin": 103,
        "ymin": 57,
        "xmax": 22,
        "ymax": 14
    },
    {
        "label": "background",
        "xmin": 0,
        "ymin": 77,
        "xmax": 37,
        "ymax": 57
    },
    {
        "label": "background",
        "xmin": 23,
        "ymin": 46,
        "xmax": 23,
        "ymax": 45
    },
    {
        "label": "background",
        "xmin": 85,
        "ymin": 51,
        "xmax": 97,
        "ymax": 45
    },
    {
        "label": "background",
        "xmin": 205,
        "ymin": 102,
        "xmax": 38,
        "ymax": 8
    },
    {
        "label": "background",
        "xmin": 0,
        "ymin": 175,
        "xmax": 61,
        "ymax": 81
    },
    {
        "label": "background",
        "xmin": 114,
        "ymin": 0,
        "xmax": 132,
        "ymax": 77
    },
    {
        "label": "background",
        "xmin": 0,
        "ymin": 230,
        "xmax": 27,
        "ymax": 26
    },
    {
        "label": "background",
        "xmin": 185,
        "ymin": 0,
        "xmax": 71,
        "ymax": 16
    },
    {
        "label": "background",
        "xmin": 0,
        "ymin": 66,
        "xmax": 36,
        "ymax": 77
    },
    {
        "label": "background",
        "xmin": 91,
        "ymin": 42,
        "xmax": 68,
        "ymax": 23
    },
    {
        "label": "background",
        "xmin": 0,
        "ymin": 234,
        "xmax": 17,
        "ymax": 12
    },
    {
        "label": "background",
        "xmin": 151,
        "ymin": 79,
        "xmax": 105,
        "ymax": 28
    },
    {
        "label": "background",
        "xmin": 0,
        "ymin": 14,
        "xmax": 44,
        "ymax": 73
    },
    {
        "label": "background",
        "xmin": 9,
        "ymin": 23,
        "xmax": 27,
        "ymax": 51
    },
    {
        "label": "background",
        "xmin": 102,
        "ymin": 211,
        "xmax": 17,
        "ymax": 17
    },
    {
        "label": "background",
        "xmin": 165,
        "ymin": 192,
        "xmax": 40,
        "ymax": 64
    },
    {
        "label": "background",
        "xmin": 4,
        "ymin": 185,
        "xmax": 21,
        "ymax": 41
    },
    {
        "label": "background",
        "xmin": 0,
        "ymin": 0,
        "xmax": 256,
        "ymax": 256
    },
    {
        "label": "background",
        "xmin": 157,
        "ymin": 223,
        "xmax": 48,
        "ymax": 33
    },
    {
        "label": "background",
        "xmin": 92,
        "ymin": 31,
        "xmax": 97,
        "ymax": 33
    },
    {
        "label": "background",
        "xmin": 0,
        "ymin": 0,
        "xmax": 37,
        "ymax": 24
    },
    {
        "label": "background",
        "xmin": 97,
        "ymin": 57,
        "xmax": 82,
        "ymax": 28
    },
    {
        "label": "background",
        "xmin": 0,
        "ymin": 0,
        "xmax": 117,
        "ymax": 94
    },
    {
        "label": "background",
        "xmin": 115,
        "ymin": 0,
        "xmax": 141,
        "ymax": 111
    },
    {
        "label": "background",
        "xmin": 155,
        "ymin": 104,
        "xmax": 37,
        "ymax": 7
    },
    {
        "label": "background",
        "xmin": 8,
        "ymin": 193,
        "xmax": 14,
        "ymax": 17
    },
    {
        "label": "background",
        "xmin": 83,
        "ymin": 42,
        "xmax": 116,
        "ymax": 57
    },
    {
        "label": "background",
        "xmin": 83,
        "ymin": 52,
        "xmax": 19,
        "ymax": 28
    },
    {
        "label": "background",
        "xmin": 107,
        "ymin": 0,
        "xmax": 140,
        "ymax": 77
    },
    {
        "label": "background",
        "xmin": 170,
        "ymin": 229,
        "xmax": 15,
        "ymax": 27
    },
    {
        "label": "background",
        "xmin": 0,
        "ymin": 118,
        "xmax": 17,
        "ymax": 25
    },
    {
        "label": "background",
        "xmin": 0,
        "ymin": 23,
        "xmax": 29,
        "ymax": 34
    },
    {
        "label": "background",
        "xmin": 29,
        "ymin": 0,
        "xmax": 88,
        "ymax": 87
    },
    {
        "label": "background",
        "xmin": 0,
        "ymin": 172,
        "xmax": 125,
        "ymax": 84
    },
    {
        "label": "background",
        "xmin": 85,
        "ymin": 211,
        "xmax": 35,
        "ymax": 24
    },
    {
        "label": "background",
        "xmin": 34,
        "ymin": 0,
        "xmax": 17,
        "ymax": 73
    },
    {
        "label": "background",
        "xmin": 82,
        "ymin": 56,
        "xmax": 51,
        "ymax": 62
    },
    {
        "label": "background",
        "xmin": 103,
        "ymin": 98,
        "xmax": 31,
        "ymax": 20
    },
    {
        "label": "background",
        "xmin": 89,
        "ymin": 92,
        "xmax": 45,
        "ymax": 33
    },
    {
        "label": "background",
        "xmin": 114,
        "ymin": 0,
        "xmax": 36,
        "ymax": 10
    },
    {
        "label": "background",
        "xmin": 83,
        "ymin": 228,
        "xmax": 42,
        "ymax": 28
    },
    {
        "label": "background",
        "xmin": 176,
        "ymin": 0,
        "xmax": 26,
        "ymax": 17
    },
    {
        "label": "background",
        "xmin": 0,
        "ymin": 175,
        "xmax": 44,
        "ymax": 81
    },
    {
        "label": "background",
        "xmin": 0,
        "ymin": 0,
        "xmax": 117,
        "ymax": 144
    },
    {
        "label": "background",
        "xmin": 171,
        "ymin": 68,
        "xmax": 34,
        "ymax": 12
    },
    {
        "label": "background",
        "xmin": 228,
        "ymin": 50,
        "xmax": 28,
        "ymax": 30
    },
    {
        "label": "background",
        "xmin": 0,
        "ymin": 70,
        "xmax": 37,
        "ymax": 64
    },
    {
        "label": "background",
        "xmin": 0,
        "ymin": 0,
        "xmax": 36,
        "ymax": 24
    },
    {
        "label": "background",
        "xmin": 155,
        "ymin": 106,
        "xmax": 28,
        "ymax": 5
    },
    {
        "label": "background",
        "xmin": 228,
        "ymin": 119,
        "xmax": 18,
        "ymax": 12
    },
    {
        "label": "background",
        "xmin": 142,
        "ymin": 50,
        "xmax": 29,
        "ymax": 13
    },
    {
        "label": "background",
        "xmin": 176,
        "ymin": 51,
        "xmax": 29,
        "ymax": 23
    },
    {
        "label": "background",
        "xmin": 115,
        "ymin": 0,
        "xmax": 129,
        "ymax": 76
    },
    {
        "label": "background",
        "xmin": 0,
        "ymin": 64,
        "xmax": 35,
        "ymax": 69
    },
    {
        "label": "background",
        "xmin": 91,
        "ymin": 79,
        "xmax": 52,
        "ymax": 20
    },
    {
        "label": "background",
        "xmin": 216,
        "ymin": 50,
        "xmax": 40,
        "ymax": 29
    },
    {
        "label": "background",
        "xmin": 193,
        "ymin": 159,
        "xmax": 20,
        "ymax": 14
    },
    {
        "label": "background",
        "xmin": 32,
        "ymin": 0,
        "xmax": 85,
        "ymax": 94
    },
    {
        "label": "background",
        "xmin": 0,
        "ymin": 77,
        "xmax": 37,
        "ymax": 66
    },
    {
        "label": "background",
        "xmin": 29,
        "ymin": 0,
        "xmax": 121,
        "ymax": 87
    },
    {
        "label": "background",
        "xmin": 142,
        "ymin": 142,
        "xmax": 29,
        "ymax": 28
    },
    {
        "label": "background",
        "xmin": 137,
        "ymin": 67,
        "xmax": 119,
        "ymax": 44
    },
    {
        "label": "background",
        "xmin": 36,
        "ymin": 28,
        "xmax": 16,
        "ymax": 47
    },
    {
        "label": "background",
        "xmin": 104,
        "ymin": 211,
        "xmax": 16,
        "ymax": 20
    },
    {
        "label": "background",
        "xmin": 0,
        "ymin": 17,
        "xmax": 36,
        "ymax": 70
    },
    {
        "label": "background",
        "xmin": 186,
        "ymin": 0,
        "xmax": 70,
        "ymax": 32
    },
    {
        "label": "background",
        "xmin": 228,
        "ymin": 28,
        "xmax": 28,
        "ymax": 18
    },
    {
        "label": "background",
        "xmin": 143,
        "ymin": 142,
        "xmax": 42,
        "ymax": 28
    },
    {
        "label": "background",
        "xmin": 83,
        "ymin": 52,
        "xmax": 60,
        "ymax": 47
    },
    {
        "label": "background",
        "xmin": 0,
        "ymin": 65,
        "xmax": 35,
        "ymax": 79
    },
    {
        "label": "background",
        "xmin": 151,
        "ymin": 84,
        "xmax": 105,
        "ymax": 23
    },
    {
        "label": "background",
        "xmin": 0,
        "ymin": 0,
        "xmax": 36,
        "ymax": 87
    },
    {
        "label": "background",
        "xmin": 85,
        "ymin": 55,
        "xmax": 17,
        "ymax": 30
    },
    {
        "label": "background",
        "xmin": 194,
        "ymin": 159,
        "xmax": 19,
        "ymax": 14
    },
    {
        "label": "background",
        "xmin": 188,
        "ymin": 67,
        "xmax": 68,
        "ymax": 21
    },
    {
        "label": "background",
        "xmin": 0,
        "ymin": 0,
        "xmax": 34,
        "ymax": 24
    },
    {
        "label": "background",
        "xmin": 102,
        "ymin": 32,
        "xmax": 80,
        "ymax": 24
    },
    {
        "label": "background",
        "xmin": 0,
        "ymin": 0,
        "xmax": 38,
        "ymax": 24
    },
    {
        "label": "background",
        "xmin": 82,
        "ymin": 62,
        "xmax": 11,
        "ymax": 31
    },
    {
        "label": "background",
        "xmin": 0,
        "ymin": 245,
        "xmax": 18,
        "ymax": 11
    },
    {
        "label": "background",
        "xmin": 27,
        "ymin": 205,
        "xmax": 20,
        "ymax": 30
    },
    {
        "label": "background",
        "xmin": 172,
        "ymin": 238,
        "xmax": 11,
        "ymax": 18
    },
    {
        "label": "background",
        "xmin": 93,
        "ymin": 92,
        "xmax": 40,
        "ymax": 26
    },
    {
        "label": "background",
        "xmin": 8,
        "ymin": 189,
        "xmax": 15,
        "ymax": 22
    },
    {
        "label": "background",
        "xmin": 187,
        "ymin": 9,
        "xmax": 36,
        "ymax": 22
    },
    {
        "label": "background",
        "xmin": 11,
        "ymin": 50,
        "xmax": 18,
        "ymax": 37
    },
    {
        "label": "background",
        "xmin": 17,
        "ymin": 77,
        "xmax": 20,
        "ymax": 17
    },
    {
        "label": "background",
        "xmin": 126,
        "ymin": 0,
        "xmax": 23,
        "ymax": 14
    },
    {
        "label": "background",
        "xmin": 165,
        "ymin": 79,
        "xmax": 91,
        "ymax": 25
    },
    {
        "label": "background",
        "xmin": 229,
        "ymin": 30,
        "xmax": 27,
        "ymax": 16
    },
    {
        "label": "background",
        "xmin": 215,
        "ymin": 31,
        "xmax": 32,
        "ymax": 20
    },
    {
        "label": "background",
        "xmin": 80,
        "ymin": 201,
        "xmax": 14,
        "ymax": 17
    },
    {
        "label": "background",
        "xmin": 115,
        "ymin": 217,
        "xmax": 43,
        "ymax": 39
    },
    {
        "label": "background",
        "xmin": 170,
        "ymin": 51,
        "xmax": 35,
        "ymax": 28
    },
    {
        "label": "background",
        "xmin": 170,
        "ymin": 223,
        "xmax": 35,
        "ymax": 33
    },
    {
        "label": "background",
        "xmin": 142,
        "ymin": 131,
        "xmax": 39,
        "ymax": 36
    },
    {
        "label": "background",
        "xmin": 143,
        "ymin": 131,
        "xmax": 39,
        "ymax": 36
    },
    {
        "label": "background",
        "xmin": 28,
        "ymin": 0,
        "xmax": 20,
        "ymax": 17
    },
    {
        "label": "background",
        "xmin": 13,
        "ymin": 0,
        "xmax": 29,
        "ymax": 91
    },
    {
        "label": "background",
        "xmin": 70,
        "ymin": 225,
        "xmax": 30,
        "ymax": 31
    },
    {
        "label": "background",
        "xmin": 52,
        "ymin": 190,
        "xmax": 59,
        "ymax": 66
    },
    {
        "label": "background",
        "xmin": 197,
        "ymin": 15,
        "xmax": 29,
        "ymax": 20
    },
    {
        "label": "background",
        "xmin": 136,
        "ymin": 122,
        "xmax": 50,
        "ymax": 45
    },
    {
        "label": "background",
        "xmin": 137,
        "ymin": 47,
        "xmax": 27,
        "ymax": 15
    },
    {
        "label": "background",
        "xmin": 23,
        "ymin": 0,
        "xmax": 18,
        "ymax": 80
    },
    {
        "label": "background",
        "xmin": 0,
        "ymin": 233,
        "xmax": 23,
        "ymax": 23
    },
    {
        "label": "background",
        "xmin": 103,
        "ymin": 211,
        "xmax": 16,
        "ymax": 20
    },
    {
        "label": "background",
        "xmin": 154,
        "ymin": 134,
        "xmax": 19,
        "ymax": 20
    },
    {
        "label": "background",
        "xmin": 185,
        "ymin": 84,
        "xmax": 71,
        "ymax": 13
    },
    {
        "label": "background",
        "xmin": 170,
        "ymin": 228,
        "xmax": 24,
        "ymax": 28
    },
    {
        "label": "background",
        "xmin": 21,
        "ymin": 78,
        "xmax": 28,
        "ymax": 18
    },
    {
        "label": "background",
        "xmin": 0,
        "ymin": 0,
        "xmax": 41,
        "ymax": 94
    },
    {
        "label": "background",
        "xmin": 171,
        "ymin": 50,
        "xmax": 85,
        "ymax": 38
    },
    {
        "label": "background",
        "xmin": 65,
        "ymin": 199,
        "xmax": 15,
        "ymax": 18
    },
    {
        "label": "background",
        "xmin": 92,
        "ymin": 35,
        "xmax": 73,
        "ymax": 29
    },
    {
        "label": "background",
        "xmin": 112,
        "ymin": 32,
        "xmax": 70,
        "ymax": 8
    },
    {
        "label": "background",
        "xmin": 0,
        "ymin": 98,
        "xmax": 32,
        "ymax": 45
    },
    {
        "label": "background",
        "xmin": 23,
        "ymin": 79,
        "xmax": 26,
        "ymax": 18
    },
    {
        "label": "background",
        "xmin": 107,
        "ymin": 21,
        "xmax": 41,
        "ymax": 17
    },
    {
        "label": "background",
        "xmin": 97,
        "ymin": 95,
        "xmax": 36,
        "ymax": 27
    },
    {
        "label": "background",
        "xmin": 136,
        "ymin": 47,
        "xmax": 28,
        "ymax": 15
    },
    {
        "label": "background",
        "xmin": 186,
        "ymin": 0,
        "xmax": 70,
        "ymax": 57
    },
    {
        "label": "background",
        "xmin": 36,
        "ymin": 0,
        "xmax": 80,
        "ymax": 87
    },
    {
        "label": "background",
        "xmin": 137,
        "ymin": 40,
        "xmax": 22,
        "ymax": 8
    },
    {
        "label": "background",
        "xmin": 12,
        "ymin": 98,
        "xmax": 20,
        "ymax": 22
    },
    {
        "label": "background",
        "xmin": 0,
        "ymin": 181,
        "xmax": 100,
        "ymax": 75
    },
    {
        "label": "background",
        "xmin": 158,
        "ymin": 103,
        "xmax": 58,
        "ymax": 8
    },
    {
        "label": "background",
        "xmin": 13,
        "ymin": 0,
        "xmax": 39,
        "ymax": 95
    },
    {
        "label": "background",
        "xmin": 0,
        "ymin": 37,
        "xmax": 37,
        "ymax": 106
    },
    {
        "label": "background",
        "xmin": 131,
        "ymin": 79,
        "xmax": 28,
        "ymax": 12
    },
    {
        "label": "background",
        "xmin": 93,
        "ymin": 85,
        "xmax": 49,
        "ymax": 11
    },
    {
        "label": "background",
        "xmin": 95,
        "ymin": 0,
        "xmax": 29,
        "ymax": 28
    },
    {
        "label": "background",
        "xmin": 151,
        "ymin": 88,
        "xmax": 105,
        "ymax": 27
    },
    {
        "label": "background",
        "xmin": 0,
        "ymin": 37,
        "xmax": 13,
        "ymax": 39
    },
    {
        "label": "background",
        "xmin": 0,
        "ymin": 234,
        "xmax": 20,
        "ymax": 22
    },
    {
        "label": "background",
        "xmin": 80,
        "ymin": 200,
        "xmax": 14,
        "ymax": 17
    },
    {
        "label": "background",
        "xmin": 136,
        "ymin": 148,
        "xmax": 46,
        "ymax": 23
    },
    {
        "label": "background",
        "xmin": 185,
        "ymin": 0,
        "xmax": 71,
        "ymax": 32
    },
    {
        "label": "background",
        "xmin": 103,
        "ymin": 57,
        "xmax": 39,
        "ymax": 13
    },
    {
        "label": "background",
        "xmin": 102,
        "ymin": 32,
        "xmax": 80,
        "ymax": 10
    },
    {
        "label": "background",
        "xmin": 0,
        "ymin": 0,
        "xmax": 117,
        "ymax": 143
    },
    {
        "label": "background",
        "xmin": 60,
        "ymin": 204,
        "xmax": 21,
        "ymax": 29
    },
    {
        "label": "background",
        "xmin": 91,
        "ymin": 79,
        "xmax": 68,
        "ymax": 20
    },
    {
        "label": "background",
        "xmin": 25,
        "ymin": 172,
        "xmax": 16,
        "ymax": 11
    },
    {
        "label": "background",
        "xmin": 173,
        "ymin": 68,
        "xmax": 26,
        "ymax": 11
    },
    {
        "label": "background",
        "xmin": 0,
        "ymin": 9,
        "xmax": 256,
        "ymax": 247
    },
    {
        "label": "background",
        "xmin": 93,
        "ymin": 74,
        "xmax": 49,
        "ymax": 22
    },
    {
        "label": "background",
        "xmin": 104,
        "ymin": 33,
        "xmax": 49,
        "ymax": 9
    },
    {
        "label": "background",
        "xmin": 0,
        "ymin": 36,
        "xmax": 12,
        "ymax": 31
    },
    {
        "label": "background",
        "xmin": 186,
        "ymin": 0,
        "xmax": 70,
        "ymax": 63
    },
    {
        "label": "background",
        "xmin": 0,
        "ymin": 36,
        "xmax": 35,
        "ymax": 97
    },
    {
        "label": "background",
        "xmin": 120,
        "ymin": 42,
        "xmax": 20,
        "ymax": 9
    },
    {
        "label": "background",
        "xmin": 186,
        "ymin": 0,
        "xmax": 70,
        "ymax": 14
    },
    {
        "label": "background",
        "xmin": 208,
        "ymin": 147,
        "xmax": 32,
        "ymax": 19
    },
    {
        "label": "background",
        "xmin": 191,
        "ymin": 3,
        "xmax": 65,
        "ymax": 54
    },
    {
        "label": "background",
        "xmin": 165,
        "ymin": 124,
        "xmax": 21,
        "ymax": 30
    },
    {
        "label": "background",
        "xmin": 17,
        "ymin": 0,
        "xmax": 24,
        "ymax": 94
    },
    {
        "label": "background",
        "xmin": 13,
        "ymin": 76,
        "xmax": 24,
        "ymax": 15
    },
    {
        "label": "background",
        "xmin": 0,
        "ymin": 0,
        "xmax": 116,
        "ymax": 134
    },
    {
        "label": "background",
        "xmin": 13,
        "ymin": 46,
        "xmax": 33,
        "ymax": 49
    },
    {
        "label": "background",
        "xmin": 73,
        "ymin": 26,
        "xmax": 22,
        "ymax": 26
    },
    {
        "label": "background",
        "xmin": 103,
        "ymin": 42,
        "xmax": 61,
        "ymax": 28
    },
    {
        "label": "background",
        "xmin": 96,
        "ymin": 74,
        "xmax": 46,
        "ymax": 17
    },
    {
        "label": "background",
        "xmin": 73,
        "ymin": 22,
        "xmax": 28,
        "ymax": 30
    },
    {
        "label": "background",
        "xmin": 29,
        "ymin": 0,
        "xmax": 9,
        "ymax": 16
    },
    {
        "label": "background",
        "xmin": 142,
        "ymin": 131,
        "xmax": 40,
        "ymax": 39
    },
    {
        "label": "background",
        "xmin": 216,
        "ymin": 58,
        "xmax": 29,
        "ymax": 15
    },
    {
        "label": "background",
        "xmin": 167,
        "ymin": 105,
        "xmax": 41,
        "ymax": 4
    },
    {
        "label": "background",
        "xmin": 136,
        "ymin": 122,
        "xmax": 18,
        "ymax": 18
    },
    {
        "label": "background",
        "xmin": 93,
        "ymin": 57,
        "xmax": 86,
        "ymax": 39
    },
    {
        "label": "background",
        "xmin": 117,
        "ymin": 0,
        "xmax": 12,
        "ymax": 22
    },
    {
        "label": "background",
        "xmin": 171,
        "ymin": 68,
        "xmax": 28,
        "ymax": 13
    },
    {
        "label": "background",
        "xmin": 198,
        "ymin": 16,
        "xmax": 28,
        "ymax": 19
    },
    {
        "label": "background",
        "xmin": 42,
        "ymin": 191,
        "xmax": 19,
        "ymax": 18
    },
    {
        "label": "background",
        "xmin": 176,
        "ymin": 0,
        "xmax": 80,
        "ymax": 57
    },
    {
        "label": "background",
        "xmin": 0,
        "ymin": 0,
        "xmax": 48,
        "ymax": 24
    },
    {
        "label": "background",
        "xmin": 6,
        "ymin": 41,
        "xmax": 10,
        "ymax": 37
    },
    {
        "label": "background",
        "xmin": 0,
        "ymin": 0,
        "xmax": 49,
        "ymax": 143
    },
    {
        "label": "background",
        "xmin": 187,
        "ymin": 9,
        "xmax": 60,
        "ymax": 42
    },
    {
        "label": "background",
        "xmin": 42,
        "ymin": 147,
        "xmax": 16,
        "ymax": 25
    },
    {
        "label": "background",
        "xmin": 52,
        "ymin": 201,
        "xmax": 52,
        "ymax": 55
    },
    {
        "label": "background",
        "xmin": 170,
        "ymin": 51,
        "xmax": 12,
        "ymax": 17
    },
    {
        "label": "background",
        "xmin": 158,
        "ymin": 104,
        "xmax": 43,
        "ymax": 7
    },
    {
        "label": "background",
        "xmin": 13,
        "ymin": 78,
        "xmax": 19,
        "ymax": 17
    },
    {
        "label": "background",
        "xmin": 137,
        "ymin": 67,
        "xmax": 119,
        "ymax": 26
    },
    {
        "label": "background",
        "xmin": 85,
        "ymin": 42,
        "xmax": 120,
        "ymax": 54
    },
    {
        "label": "background",
        "xmin": 0,
        "ymin": 0,
        "xmax": 42,
        "ymax": 143
    },
    {
        "label": "background",
        "xmin": 35,
        "ymin": 191,
        "xmax": 26,
        "ymax": 32
    },
    {
        "label": "background",
        "xmin": 0,
        "ymin": 36,
        "xmax": 12,
        "ymax": 34
    },
    {
        "label": "background",
        "xmin": 108,
        "ymin": 36,
        "xmax": 57,
        "ymax": 20
    },
    {
        "label": "background",
        "xmin": 0,
        "ymin": 34,
        "xmax": 13,
        "ymax": 48
    },
    {
        "label": "background",
        "xmin": 151,
        "ymin": 79,
        "xmax": 105,
        "ymax": 31
    },
    {
        "label": "background",
        "xmin": 108,
        "ymin": 42,
        "xmax": 33,
        "ymax": 9
    },
    {
        "label": "background",
        "xmin": 176,
        "ymin": 79,
        "xmax": 69,
        "ymax": 8
    },
    {
        "label": "background",
        "xmin": 229,
        "ymin": 30,
        "xmax": 27,
        "ymax": 14
    },
    {
        "label": "background",
        "xmin": 103,
        "ymin": 58,
        "xmax": 22,
        "ymax": 12
    },
    {
        "label": "background",
        "xmin": 187,
        "ymin": 9,
        "xmax": 69,
        "ymax": 70
    },
    {
        "label": "background",
        "xmin": 82,
        "ymin": 21,
        "xmax": 123,
        "ymax": 97
    },
    {
        "label": "background",
        "xmin": 0,
        "ymin": 34,
        "xmax": 37,
        "ymax": 100
    },
    {
        "label": "background",
        "xmin": 82,
        "ymin": 0,
        "xmax": 174,
        "ymax": 118
    },
    {
        "label": "background",
        "xmin": 0,
        "ymin": 65,
        "xmax": 15,
        "ymax": 17
    },
    {
        "label": "background",
        "xmin": 82,
        "ymin": 56,
        "xmax": 14,
        "ymax": 37
    },
    {
        "label": "background",
        "xmin": 188,
        "ymin": 50,
        "xmax": 68,
        "ymax": 38
    },
    {
        "label": "background",
        "xmin": 210,
        "ymin": 0,
        "xmax": 46,
        "ymax": 15
    },
    {
        "label": "background",
        "xmin": 186,
        "ymin": 0,
        "xmax": 70,
        "ymax": 79
    },
    {
        "label": "background",
        "xmin": 0,
        "ymin": 181,
        "xmax": 120,
        "ymax": 75
    },
    {
        "label": "background",
        "xmin": 79,
        "ymin": 201,
        "xmax": 15,
        "ymax": 19
    },
    {
        "label": "background",
        "xmin": 137,
        "ymin": 67,
        "xmax": 119,
        "ymax": 42
    },
    {
        "label": "background",
        "xmin": 0,
        "ymin": 0,
        "xmax": 52,
        "ymax": 95
    },
    {
        "label": "background",
        "xmin": 127,
        "ymin": 216,
        "xmax": 23,
        "ymax": 17
    },
    {
        "label": "background",
        "xmin": 0,
        "ymin": 70,
        "xmax": 37,
        "ymax": 73
    },
    {
        "label": "background",
        "xmin": 120,
        "ymin": 42,
        "xmax": 44,
        "ymax": 20
    },
    {
        "label": "background",
        "xmin": 147,
        "ymin": 31,
        "xmax": 42,
        "ymax": 9
    },
    {
        "label": "background",
        "xmin": 28,
        "ymin": 0,
        "xmax": 14,
        "ymax": 79
    },
    {
        "label": "background",
        "xmin": 42,
        "ymin": 149,
        "xmax": 16,
        "ymax": 23
    },
    {
        "label": "background",
        "xmin": 85,
        "ymin": 55,
        "xmax": 57,
        "ymax": 41
    },
    {
        "label": "background",
        "xmin": 137,
        "ymin": 67,
        "xmax": 119,
        "ymax": 48
    },
    {
        "label": "background",
        "xmin": 83,
        "ymin": 0,
        "xmax": 173,
        "ymax": 99
    },
    {
        "label": "background",
        "xmin": 0,
        "ymin": 23,
        "xmax": 36,
        "ymax": 51
    },
    {
        "label": "background",
        "xmin": 85,
        "ymin": 42,
        "xmax": 97,
        "ymax": 54
    },
    {
        "label": "background",
        "xmin": 216,
        "ymin": 50,
        "xmax": 40,
        "ymax": 30
    },
    {
        "label": "background",
        "xmin": 0,
        "ymin": 23,
        "xmax": 29,
        "ymax": 64
    },
    {
        "label": "background",
        "xmin": 0,
        "ymin": 36,
        "xmax": 37,
        "ymax": 98
    },
    {
        "label": "background",
        "xmin": 0,
        "ymin": 234,
        "xmax": 18,
        "ymax": 22
    },
    {
        "label": "background",
        "xmin": 85,
        "ymin": 35,
        "xmax": 97,
        "ymax": 61
    },
    {
        "label": "background",
        "xmin": 114,
        "ymin": 0,
        "xmax": 142,
        "ymax": 80
    },
    {
        "label": "background",
        "xmin": 108,
        "ymin": 42,
        "xmax": 56,
        "ymax": 20
    },
    {
        "label": "background",
        "xmin": 83,
        "ymin": 211,
        "xmax": 42,
        "ymax": 45
    },
    {
        "label": "background",
        "xmin": 92,
        "ymin": 21,
        "xmax": 97,
        "ymax": 43
    },
    {
        "label": "background",
        "xmin": 96,
        "ymin": 57,
        "xmax": 83,
        "ymax": 34
    },
    {
        "label": "background",
        "xmin": 215,
        "ymin": 31,
        "xmax": 41,
        "ymax": 48
    },
    {
        "label": "background",
        "xmin": 0,
        "ymin": 36,
        "xmax": 15,
        "ymax": 46
    },
    {
        "label": "background",
        "xmin": 171,
        "ymin": 0,
        "xmax": 85,
        "ymax": 88
    },
    {
        "label": "background",
        "xmin": 85,
        "ymin": 31,
        "xmax": 104,
        "ymax": 65
    },
    {
        "label": "background",
        "xmin": 158,
        "ymin": 79,
        "xmax": 98,
        "ymax": 32
    },
    {
        "label": "background",
        "xmin": 136,
        "ymin": 122,
        "xmax": 50,
        "ymax": 49
    },
    {
        "label": "background",
        "xmin": 143,
        "ymin": 131,
        "xmax": 42,
        "ymax": 39
    },
    {
        "label": "background",
        "xmin": 170,
        "ymin": 51,
        "xmax": 35,
        "ymax": 23
    },
    {
        "label": "background",
        "xmin": 85,
        "ymin": 0,
        "xmax": 171,
        "ymax": 96
    },
    {
        "label": "background",
        "xmin": 82,
        "ymin": 55,
        "xmax": 20,
        "ymax": 38
    },
    {
        "label": "background",
        "xmin": 170,
        "ymin": 51,
        "xmax": 29,
        "ymax": 28
    },
    {
        "label": "background",
        "xmin": 0,
        "ymin": 37,
        "xmax": 37,
        "ymax": 97
    },
    {
        "label": "background",
        "xmin": 85,
        "ymin": 42,
        "xmax": 114,
        "ymax": 54
    },
    {
        "label": "background",
        "xmin": 34,
        "ymin": 0,
        "xmax": 18,
        "ymax": 75
    },
    {
        "label": "background",
        "xmin": 0,
        "ymin": 0,
        "xmax": 44,
        "ymax": 87
    },
    {
        "label": "background",
        "xmin": 0,
        "ymin": 0,
        "xmax": 117,
        "ymax": 133
    },
    {
        "label": "background",
        "xmin": 52,
        "ymin": 190,
        "xmax": 68,
        "ymax": 66
    },
    {
        "label": "background",
        "xmin": 103,
        "ymin": 47,
        "xmax": 61,
        "ymax": 23
    },
    {
        "label": "background",
        "xmin": 142,
        "ymin": 124,
        "xmax": 44,
        "ymax": 43
    },
    {
        "label": "background",
        "xmin": 85,
        "ymin": 31,
        "xmax": 120,
        "ymax": 65
    },
    {
        "label": "background",
        "xmin": 0,
        "ymin": 0,
        "xmax": 42,
        "ymax": 91
    },
    {
        "label": "background",
        "xmin": 73,
        "ymin": 0,
        "xmax": 51,
        "ymax": 52
    },
    {
        "label": "background",
        "xmin": 136,
        "ymin": 124,
        "xmax": 50,
        "ymax": 47
    },
    {
        "label": "background",
        "xmin": 83,
        "ymin": 51,
        "xmax": 99,
        "ymax": 45
    },
    {
        "label": "background",
        "xmin": 0,
        "ymin": 172,
        "xmax": 100,
        "ymax": 84
    },
    {
        "label": "background",
        "xmin": 91,
        "ymin": 42,
        "xmax": 88,
        "ymax": 54
    },
    {
        "label": "background",
        "xmin": 0,
        "ymin": 77,
        "xmax": 49,
        "ymax": 66
    },
    {
        "label": "background",
        "xmin": 0,
        "ymin": 0,
        "xmax": 37,
        "ymax": 87
    },
    {
        "label": "background",
        "xmin": 0,
        "ymin": 0,
        "xmax": 37,
        "ymax": 133
    },
    {
        "label": "background",
        "xmin": 82,
        "ymin": 0,
        "xmax": 174,
        "ymax": 96
    },
    {
        "label": "background",
        "xmin": 0,
        "ymin": 23,
        "xmax": 36,
        "ymax": 64
    },
    {
        "label": "background",
        "xmin": 36,
        "ymin": 0,
        "xmax": 88,
        "ymax": 87
    },
    {
        "label": "background",
        "xmin": 142,
        "ymin": 50,
        "xmax": 63,
        "ymax": 29
    },
    {
        "label": "background",
        "xmin": 0,
        "ymin": 0,
        "xmax": 116,
        "ymax": 143
    },
    {
        "label": "background",
        "xmin": 91,
        "ymin": 0,
        "xmax": 155,
        "ymax": 91
    },
    {
        "label": "background",
        "xmin": 107,
        "ymin": 0,
        "xmax": 149,
        "ymax": 88
    },
    {
        "label": "background",
        "xmin": 176,
        "ymin": 0,
        "xmax": 80,
        "ymax": 80
    },
    {
        "label": "background",
        "xmin": 115,
        "ymin": 0,
        "xmax": 141,
        "ymax": 79
    },
    {
        "label": "background",
        "xmin": 83,
        "ymin": 42,
        "xmax": 99,
        "ymax": 57
    },
    {
        "label": "background",
        "xmin": 83,
        "ymin": 42,
        "xmax": 99,
        "ymax": 54
    },
    {
        "label": "background",
        "xmin": 13,
        "ymin": 28,
        "xmax": 39,
        "ymax": 67
    },
    {
        "label": "background",
        "xmin": 82,
        "ymin": 55,
        "xmax": 60,
        "ymax": 41
    },
    {
        "label": "background",
        "xmin": 0,
        "ymin": 0,
        "xmax": 150,
        "ymax": 143
    },
    {
        "label": "background",
        "xmin": 151,
        "ymin": 79,
        "xmax": 105,
        "ymax": 30
    },
    {
        "label": "background",
        "xmin": 142,
        "ymin": 50,
        "xmax": 57,
        "ymax": 29
    },
    {
        "label": "background",
        "xmin": 0,
        "ymin": 34,
        "xmax": 49,
        "ymax": 100
    },
    {
        "label": "background",
        "xmin": 0,
        "ymin": 0,
        "xmax": 38,
        "ymax": 87
    },
    {
        "label": "background",
        "xmin": 96,
        "ymin": 36,
        "xmax": 109,
        "ymax": 55
    },
    {
        "label": "background",
        "xmin": 0,
        "ymin": 36,
        "xmax": 49,
        "ymax": 98
    },
    {
        "label": "background",
        "xmin": 0,
        "ymin": 172,
        "xmax": 120,
        "ymax": 84
    },
    {
        "label": "background",
        "xmin": 0,
        "ymin": 0,
        "xmax": 37,
        "ymax": 143
    },
    {
        "label": "background",
        "xmin": 82,
        "ymin": 0,
        "xmax": 174,
        "ymax": 125
    },
    {
        "label": "background",
        "xmin": 0,
        "ymin": 0,
        "xmax": 52,
        "ymax": 143
    },
    {
        "label": "background",
        "xmin": 0,
        "ymin": 0,
        "xmax": 117,
        "ymax": 134
    },
    {
        "label": "background",
        "xmin": 0,
        "ymin": 0,
        "xmax": 41,
        "ymax": 133
    },
    {
        "label": "background",
        "xmin": 73,
        "ymin": 0,
        "xmax": 183,
        "ymax": 125
    },
    {
        "label": "background",
        "xmin": 82,
        "ymin": 32,
        "xmax": 123,
        "ymax": 93
    },
    {
        "label": "background",
        "xmin": 96,
        "ymin": 50,
        "xmax": 109,
        "ymax": 41
    },
    {
        "label": "background",
        "xmin": 0,
        "ymin": 0,
        "xmax": 124,
        "ymax": 143
    },
    {
        "label": "background",
        "xmin": 82,
        "ymin": 42,
        "xmax": 97,
        "ymax": 54
    },
    {
        "label": "background",
        "xmin": 82,
        "ymin": 31,
        "xmax": 123,
        "ymax": 87
    },
    {
        "label": "background",
        "xmin": 0,
        "ymin": 0,
        "xmax": 256,
        "ymax": 143
    },
    {
        "label": "background",
        "xmin": 85,
        "ymin": 21,
        "xmax": 120,
        "ymax": 75
    },
    {
        "label": "background",
        "xmin": 114,
        "ymin": 0,
        "xmax": 142,
        "ymax": 115
    },
    {
        "label": "background",
        "xmin": 91,
        "ymin": 36,
        "xmax": 114,
        "ymax": 55
    },
    {
        "label": "background",
        "xmin": 82,
        "ymin": 42,
        "xmax": 123,
        "ymax": 54
    },
    {
        "label": "background",
        "xmin": 83,
        "ymin": 0,
        "xmax": 164,
        "ymax": 99
    },
    {
        "label": "background",
        "xmin": 73,
        "ymin": 0,
        "xmax": 183,
        "ymax": 96
    },
    {
        "label": "background",
        "xmin": 82,
        "ymin": 32,
        "xmax": 123,
        "ymax": 64
    },
    {
        "label": "background",
        "xmin": 85,
        "ymin": 0,
        "xmax": 159,
        "ymax": 96
    },
    {
        "label": "background",
        "xmin": 91,
        "ymin": 0,
        "xmax": 165,
        "ymax": 91
    },
    {
        "label": "background",
        "xmin": 73,
        "ymin": 0,
        "xmax": 183,
        "ymax": 115
    }
]