[
    {
        "label": "background",
        "xmin": 102,
        "ymin": 246,
        "xmax": 22,
        "ymax": 10
    },
    {
        "label": "background",
        "xmin": 20,
        "ymin": 132,
        "xmax": 27,
        "ymax": 12
    },
    {
        "label": "background",
        "xmin": 201,
        "ymin": 109,
        "xmax": 6,
        "ymax": 27
    },
    {
        "label": "background",
        "xmin": 128,
        "ymin": 223,
        "xmax": 48,
        "ymax": 33
    },
    {
        "label": "background",
        "xmin": 220,
        "ymin": 204,
        "xmax": 36,
        "ymax": 25
    },
    {
        "label": "background",
        "xmin": 215,
        "ymin": 245,
        "xmax": 11,
        "ymax": 11
    },
    {
        "label": "background",
        "xmin": 62,
        "ymin": 53,
        "xmax": 92,
        "ymax": 39
    },
    {
        "label": "background",
        "xmin": 0,
        "ymin": 80,
        "xmax": 77,
        "ymax": 46
    },
    {
        "label": "background",
        "xmin": 78,
        "ymin": 168,
        "xmax": 25,
        "ymax": 10
    },
    {
        "label": "background",
        "xmin": 157,
        "ymin": 91,
        "xmax": 99,
        "ymax": 73
    },
    {
        "label": "background",
        "xmin": 152,
        "ymin": 86,
        "xmax": 36,
        "ymax": 10
    },
    {
        "label": "background",
        "xmin": 114,
        "ymin": 158,
        "xmax": 32,
        "ymax": 19
    },
    {
        "label": "background",
        "xmin": 40,
        "ymin": 128,
        "xmax": 22,
        "ymax": 9
    },
    {
        "label": "background",
        "xmin": 82,
        "ymin": 157,
        "xmax": 41,
        "ymax": 28
    },
    {
        "label": "background",
        "xmin": 60,
        "ymin": 156,
        "xmax": 32,
        "ymax": 39
    },
    {
        "label": "background",
        "xmin": 112,
        "ymin": 86,
        "xmax": 144,
        "ymax": 113
    },
    {
        "label": "background",
        "xmin": 96,
        "ymin": 82,
        "xmax": 58,
        "ymax": 8
    },
    {
        "label": "background",
        "xmin": 61,
        "ymin": 97,
        "xmax": 58,
        "ymax": 28
    },
    {
        "label": "background",
        "xmin": 0,
        "ymin": 74,
        "xmax": 256,
        "ymax": 124
    },
    {
        "label": "background",
        "xmin": 189,
        "ymin": 145,
        "xmax": 25,
        "ymax": 21
    },
    {
        "label": "background",
        "xmin": 93,
        "ymin": 148,
        "xmax": 60,
        "ymax": 29
    },
    {
        "label": "background",
        "xmin": 0,
        "ymin": 234,
        "xmax": 24,
        "ymax": 22
    },
    {
        "label": "background",
        "xmin": 84,
        "ymin": 85,
        "xmax": 38,
        "ymax": 23
    },
    {
        "label": "background",
        "xmin": 103,
        "ymin": 233,
        "xmax": 52,
        "ymax": 23
    },
    {
        "label": "background",
        "xmin": 114,
        "ymin": 162,
        "xmax": 38,
        "ymax": 15
    },
    {
        "label": "background",
        "xmin": 62,
        "ymin": 75,
        "xmax": 17,
        "ymax": 16
    },
    {
        "label": "background",
        "xmin": 0,
        "ymin": 57,
        "xmax": 74,
        "ymax": 29
    },
    {
        "label": "background",
        "xmin": 62,
        "ymin": 65,
        "xmax": 40,
        "ymax": 23
    },
    {
        "label": "background",
        "xmin": 95,
        "ymin": 67,
        "xmax": 84,
        "ymax": 25
    },
    {
        "label": "background",
        "xmin": 92,
        "ymin": 199,
        "xmax": 92,
        "ymax": 57
    },
    {
        "label": "background",
        "xmin": 92,
        "ymin": 150,
        "xmax": 164,
        "ymax": 106
    },
    {
        "label": "background",
        "xmin": 77,
        "ymin": 168,
        "xmax": 25,
        "ymax": 11
    },
    {
        "label": "background",
        "xmin": 111,
        "ymin": 126,
        "xmax": 36,
        "ymax": 33
    },
    {
        "label": "background",
        "xmin": 98,
        "ymin": 229,
        "xmax": 73,
        "ymax": 27
    },
    {
        "label": "background",
        "xmin": 0,
        "ymin": 52,
        "xmax": 79,
        "ymax": 34
    },
    {
        "label": "background",
        "xmin": 51,
        "ymin": 246,
        "xmax": 26,
        "ymax": 10
    },
    {
        "label": "background",
        "xmin": 161,
        "ymin": 107,
        "xmax": 6,
        "ymax": 36
    },
    {
        "label": "background",
        "xmin": 100,
        "ymin": 180,
        "xmax": 44,
        "ymax": 13
    },
    {
        "label": "background",
        "xmin": 130,
        "ymin": 94,
        "xmax": 53,
        "ymax": 58
    },
    {
        "label": "background",
        "xmin": 0,
        "ymin": 0,
        "xmax": 256,
        "ymax": 94
    },
    {
        "label": "background",
        "xmin": 94,
        "ymin": 83,
        "xmax": 144,
        "ymax": 14
    },
    {
        "label": "background",
        "xmin": 129,
        "ymin": 150,
        "xmax": 24,
        "ymax": 26
    },
    {
        "label": "background",
        "xmin": 103,
        "ymin": 165,
        "xmax": 153,
        "ymax": 91
    },
    {
        "label": "background",
        "xmin": 89,
        "ymin": 93,
        "xmax": 167,
        "ymax": 110
    },
    {
        "label": "background",
        "xmin": 164,
        "ymin": 246,
        "xmax": 10,
        "ymax": 10
    },
    {
        "label": "background",
        "xmin": 185,
        "ymin": 83,
        "xmax": 30,
        "ymax": 11
    },
    {
        "label": "background",
        "xmin": 51,
        "ymin": 97,
        "xmax": 68,
        "ymax": 30
    },
    {
        "label": "background",
        "xmin": 108,
        "ymin": 126,
        "xmax": 36,
        "ymax": 25
    },
    {
        "label": "background",
        "xmin": 67,
        "ymin": 65,
        "xmax": 35,
        "ymax": 20
    },
    {
        "label": "background",
        "xmin": 0,
        "ymin": 54,
        "xmax": 77,
        "ymax": 72
    },
    {
        "label": "background",
        "xmin": 81,
        "ymin": 139,
        "xmax": 71,
        "ymax": 54
    },
    {
        "label": "background",
        "xmin": 108,
        "ymin": 221,
        "xmax": 32,
        "ymax": 13
    },
    {
        "label": "background",
        "xmin": 108,
        "ymin": 148,
        "xmax": 28,
        "ymax": 10
    },
    {
        "label": "background",
        "xmin": 41,
        "ymin": 84,
        "xmax": 111,
        "ymax": 22
    },
    {
        "label": "background",
        "xmin": 235,
        "ymin": 246,
        "xmax": 11,
        "ymax": 10
    },
    {
        "label": "background",
        "xmin": 0,
        "ymin": 70,
        "xmax": 14,
        "ymax": 15
    },
    {
        "label": "background",
        "xmin": 190,
        "ymin": 145,
        "xmax": 22,
        "ymax": 18
    },
    {
        "label": "background",
        "xmin": 225,
        "ymin": 231,
        "xmax": 11,
        "ymax": 10
    },
    {
        "label": "background",
        "xmin": 69,
        "ymin": 61,
        "xmax": 35,
        "ymax": 18
    },
    {
        "label": "background",
        "xmin": 153,
        "ymin": 158,
        "xmax": 59,
        "ymax": 34
    },
    {
        "label": "background",
        "xmin": 154,
        "ymin": 61,
        "xmax": 38,
        "ymax": 21
    },
    {
        "label": "background",
        "xmin": 101,
        "ymin": 181,
        "xmax": 29,
        "ymax": 11
    },
    {
        "label": "background",
        "xmin": 119,
        "ymin": 206,
        "xmax": 33,
        "ymax": 25
    },
    {
        "label": "background",
        "xmin": 0,
        "ymin": 107,
        "xmax": 256,
        "ymax": 149
    },
    {
        "label": "background",
        "xmin": 167,
        "ymin": 165,
        "xmax": 12,
        "ymax": 26
    },
    {
        "label": "background",
        "xmin": 187,
        "ymin": 91,
        "xmax": 45,
        "ymax": 11
    },
    {
        "label": "background",
        "xmin": 89,
        "ymin": 107,
        "xmax": 43,
        "ymax": 40
    },
    {
        "label": "background",
        "xmin": 26,
        "ymin": 84,
        "xmax": 41,
        "ymax": 7
    },
    {
        "label": "background",
        "xmin": 220,
        "ymin": 201,
        "xmax": 36,
        "ymax": 28
    },
    {
        "label": "background",
        "xmin": 119,
        "ymin": 91,
        "xmax": 50,
        "ymax": 52
    },
    {
        "label": "background",
        "xmin": 0,
        "ymin": 63,
        "xmax": 11,
        "ymax": 12
    },
    {
        "label": "background",
        "xmin": 81,
        "ymin": 140,
        "xmax": 40,
        "ymax": 10
    },
    {
        "label": "background",
        "xmin": 0,
        "ymin": 149,
        "xmax": 126,
        "ymax": 107
    },
    {
        "label": "background",
        "xmin": 133,
        "ymin": 183,
        "xmax": 10,
        "ymax": 16
    },
    {
        "label": "background",
        "xmin": 81,
        "ymin": 93,
        "xmax": 71,
        "ymax": 26
    },
    {
        "label": "background",
        "xmin": 0,
        "ymin": 74,
        "xmax": 108,
        "ymax": 77
    },
    {
        "label": "background",
        "xmin": 0,
        "ymin": 0,
        "xmax": 256,
        "ymax": 87
    },
    {
        "label": "background",
        "xmin": 182,
        "ymin": 172,
        "xmax": 69,
        "ymax": 32
    },
    {
        "label": "background",
        "xmin": 220,
        "ymin": 86,
        "xmax": 36,
        "ymax": 9
    },
    {
        "label": "background",
        "xmin": 37,
        "ymin": 83,
        "xmax": 31,
        "ymax": 9
    },
    {
        "label": "background",
        "xmin": 84,
        "ymin": 140,
        "xmax": 38,
        "ymax": 10
    },
    {
        "label": "background",
        "xmin": 95,
        "ymin": 82,
        "xmax": 64,
        "ymax": 10
    },
    {
        "label": "background",
        "xmin": 153,
        "ymin": 158,
        "xmax": 39,
        "ymax": 34
    },
    {
        "label": "background",
        "xmin": 0,
        "ymin": 98,
        "xmax": 57,
        "ymax": 28
    },
    {
        "label": "background",
        "xmin": 25,
        "ymin": 84,
        "xmax": 41,
        "ymax": 7
    },
    {
        "label": "background",
        "xmin": 143,
        "ymin": 213,
        "xmax": 30,
        "ymax": 32
    },
    {
        "label": "background",
        "xmin": 0,
        "ymin": 107,
        "xmax": 130,
        "ymax": 149
    },
    {
        "label": "background",
        "xmin": 0,
        "ymin": 0,
        "xmax": 256,
        "ymax": 84
    },
    {
        "label": "background",
        "xmin": 79,
        "ymin": 170,
        "xmax": 21,
        "ymax": 7
    },
    {
        "label": "background",
        "xmin": 211,
        "ymin": 78,
        "xmax": 45,
        "ymax": 15
    },
    {
        "label": "background",
        "xmin": 219,
        "ymin": 198,
        "xmax": 37,
        "ymax": 31
    },
    {
        "label": "background",
        "xmin": 92,
        "ymin": 143,
        "xmax": 33,
        "ymax": 8
    },
    {
        "label": "background",
        "xmin": 0,
        "ymin": 74,
        "xmax": 90,
        "ymax": 44
    },
    {
        "label": "background",
        "xmin": 102,
        "ymin": 232,
        "xmax": 52,
        "ymax": 24
    },
    {
        "label": "background",
        "xmin": 0,
        "ymin": 57,
        "xmax": 256,
        "ymax": 77
    },
    {
        "label": "background",
        "xmin": 101,
        "ymin": 162,
        "xmax": 51,
        "ymax": 31
    },
    {
        "label": "background",
        "xmin": 159,
        "ymin": 165,
        "xmax": 16,
        "ymax": 21
    },
    {
        "label": "background",
        "xmin": 204,
        "ymin": 65,
        "xmax": 12,
        "ymax": 10
    },
    {
        "label": "background",
        "xmin": 175,
        "ymin": 68,
        "xmax": 20,
        "ymax": 7
    },
    {
        "label": "background",
        "xmin": 63,
        "ymin": 53,
        "xmax": 54,
        "ymax": 36
    },
    {
        "label": "background",
        "xmin": 217,
        "ymin": 114,
        "xmax": 39,
        "ymax": 65
    },
    {
        "label": "background",
        "xmin": 40,
        "ymin": 127,
        "xmax": 23,
        "ymax": 11
    },
    {
        "label": "background",
        "xmin": 182,
        "ymin": 172,
        "xmax": 27,
        "ymax": 19
    },
    {
        "label": "background",
        "xmin": 150,
        "ymin": 213,
        "xmax": 23,
        "ymax": 32
    },
    {
        "label": "background",
        "xmin": 0,
        "ymin": 80,
        "xmax": 77,
        "ymax": 25
    },
    {
        "label": "background",
        "xmin": 143,
        "ymin": 233,
        "xmax": 24,
        "ymax": 23
    },
    {
        "label": "background",
        "xmin": 83,
        "ymin": 108,
        "xmax": 29,
        "ymax": 16
    },
    {
        "label": "background",
        "xmin": 0,
        "ymin": 127,
        "xmax": 63,
        "ymax": 25
    },
    {
        "label": "background",
        "xmin": 163,
        "ymin": 172,
        "xmax": 26,
        "ymax": 21
    },
    {
        "label": "background",
        "xmin": 129,
        "ymin": 91,
        "xmax": 38,
        "ymax": 46
    },
    {
        "label": "background",
        "xmin": 101,
        "ymin": 164,
        "xmax": 46,
        "ymax": 17
    },
    {
        "label": "background",
        "xmin": 0,
        "ymin": 54,
        "xmax": 44,
        "ymax": 31
    },
    {
        "label": "background",
        "xmin": 249,
        "ymin": 113,
        "xmax": 7,
        "ymax": 28
    },
    {
        "label": "background",
        "xmin": 183,
        "ymin": 109,
        "xmax": 56,
        "ymax": 56
    },
    {
        "label": "background",
        "xmin": 0,
        "ymin": 54,
        "xmax": 75,
        "ymax": 33
    },
    {
        "label": "background",
        "xmin": 143,
        "ymin": 88,
        "xmax": 113,
        "ymax": 65
    },
    {
        "label": "background",
        "xmin": 183,
        "ymin": 109,
        "xmax": 73,
        "ymax": 71
    },
    {
        "label": "background",
        "xmin": 102,
        "ymin": 222,
        "xmax": 51,
        "ymax": 24
    },
    {
        "label": "background",
        "xmin": 124,
        "ymin": 91,
        "xmax": 32,
        "ymax": 17
    },
    {
        "label": "background",
        "xmin": 180,
        "ymin": 91,
        "xmax": 12,
        "ymax": 60
    },
    {
        "label": "background",
        "xmin": 152,
        "ymin": 212,
        "xmax": 32,
        "ymax": 34
    },
    {
        "label": "background",
        "xmin": 157,
        "ymin": 67,
        "xmax": 99,
        "ymax": 28
    },
    {
        "label": "background",
        "xmin": 99,
        "ymin": 179,
        "xmax": 33,
        "ymax": 15
    },
    {
        "label": "background",
        "xmin": 0,
        "ymin": 0,
        "xmax": 256,
        "ymax": 82
    },
    {
        "label": "background",
        "xmin": 123,
        "ymin": 212,
        "xmax": 64,
        "ymax": 44
    },
    {
        "label": "background",
        "xmin": 112,
        "ymin": 94,
        "xmax": 144,
        "ymax": 104
    },
    {
        "label": "background",
        "xmin": 87,
        "ymin": 199,
        "xmax": 53,
        "ymax": 35
    },
    {
        "label": "background",
        "xmin": 26,
        "ymin": 64,
        "xmax": 93,
        "ymax": 28
    },
    {
        "label": "background",
        "xmin": 184,
        "ymin": 77,
        "xmax": 72,
        "ymax": 18
    },
    {
        "label": "background",
        "xmin": 185,
        "ymin": 83,
        "xmax": 53,
        "ymax": 17
    },
    {
        "label": "background",
        "xmin": 130,
        "ymin": 94,
        "xmax": 53,
        "ymax": 51
    },
    {
        "label": "background",
        "xmin": 81,
        "ymin": 140,
        "xmax": 77,
        "ymax": 53
    },
    {
        "label": "background",
        "xmin": 91,
        "ymin": 143,
        "xmax": 67,
        "ymax": 30
    },
    {
        "label": "background",
        "xmin": 60,
        "ymin": 146,
        "xmax": 196,
        "ymax": 110
    },
    {
        "label": "background",
        "xmin": 62,
        "ymin": 64,
        "xmax": 57,
        "ymax": 28
    },
    {
        "label": "background",
        "xmin": 144,
        "ymin": 231,
        "xmax": 40,
        "ymax": 25
    },
    {
        "label": "background",
        "xmin": 83,
        "ymin": 90,
        "xmax": 69,
        "ymax": 16
    },
    {
        "label": "background",
        "xmin": 0,
        "ymin": 74,
        "xmax": 110,
        "ymax": 73
    },
    {
        "label": "background",
        "xmin": 77,
        "ymin": 168,
        "xmax": 25,
        "ymax": 12
    },
    {
        "label": "background",
        "xmin": 221,
        "ymin": 86,
        "xmax": 35,
        "ymax": 7
    },
    {
        "label": "background",
        "xmin": 0,
        "ymin": 74,
        "xmax": 152,
        "ymax": 73
    },
    {
        "label": "background",
        "xmin": 81,
        "ymin": 139,
        "xmax": 175,
        "ymax": 117
    },
    {
        "label": "background",
        "xmin": 59,
        "ymin": 83,
        "xmax": 41,
        "ymax": 36
    },
    {
        "label": "background",
        "xmin": 187,
        "ymin": 92,
        "xmax": 69,
        "ymax": 11
    },
    {
        "label": "background",
        "xmin": 202,
        "ymin": 83,
        "xmax": 54,
        "ymax": 12
    },
    {
        "label": "background",
        "xmin": 101,
        "ymin": 180,
        "xmax": 30,
        "ymax": 13
    },
    {
        "label": "background",
        "xmin": 111,
        "ymin": 117,
        "xmax": 15,
        "ymax": 17
    },
    {
        "label": "background",
        "xmin": 152,
        "ymin": 92,
        "xmax": 16,
        "ymax": 17
    },
    {
        "label": "background",
        "xmin": 182,
        "ymin": 171,
        "xmax": 31,
        "ymax": 20
    },
    {
        "label": "background",
        "xmin": 77,
        "ymin": 168,
        "xmax": 26,
        "ymax": 12
    },
    {
        "label": "background",
        "xmin": 112,
        "ymin": 67,
        "xmax": 67,
        "ymax": 22
    },
    {
        "label": "background",
        "xmin": 140,
        "ymin": 228,
        "xmax": 34,
        "ymax": 28
    },
    {
        "label": "background",
        "xmin": 202,
        "ymin": 83,
        "xmax": 18,
        "ymax": 10
    },
    {
        "label": "background",
        "xmin": 102,
        "ymin": 213,
        "xmax": 82,
        "ymax": 43
    },
    {
        "label": "background",
        "xmin": 174,
        "ymin": 149,
        "xmax": 31,
        "ymax": 14
    },
    {
        "label": "background",
        "xmin": 207,
        "ymin": 187,
        "xmax": 30,
        "ymax": 32
    },
    {
        "label": "background",
        "xmin": 182,
        "ymin": 172,
        "xmax": 30,
        "ymax": 18
    },
    {
        "label": "background",
        "xmin": 16,
        "ymin": 59,
        "xmax": 59,
        "ymax": 28
    },
    {
        "label": "background",
        "xmin": 58,
        "ymin": 97,
        "xmax": 21,
        "ymax": 13
    },
    {
        "label": "background",
        "xmin": 35,
        "ymin": 75,
        "xmax": 44,
        "ymax": 18
    },
    {
        "label": "background",
        "xmin": 211,
        "ymin": 189,
        "xmax": 45,
        "ymax": 22
    },
    {
        "label": "background",
        "xmin": 124,
        "ymin": 91,
        "xmax": 33,
        "ymax": 17
    },
    {
        "label": "background",
        "xmin": 92,
        "ymin": 146,
        "xmax": 45,
        "ymax": 12
    },
    {
        "label": "background",
        "xmin": 0,
        "ymin": 80,
        "xmax": 256,
        "ymax": 176
    },
    {
        "label": "background",
        "xmin": 10,
        "ymin": 138,
        "xmax": 24,
        "ymax": 14
    },
    {
        "label": "background",
        "xmin": 153,
        "ymin": 91,
        "xmax": 14,
        "ymax": 46
    },
    {
        "label": "background",
        "xmin": 84,
        "ymin": 126,
        "xmax": 74,
        "ymax": 54
    },
    {
        "label": "background",
        "xmin": 81,
        "ymin": 139,
        "xmax": 57,
        "ymax": 24
    },
    {
        "label": "background",
        "xmin": 130,
        "ymin": 91,
        "xmax": 126,
        "ymax": 73
    },
    {
        "label": "background",
        "xmin": 15,
        "ymin": 63,
        "xmax": 52,
        "ymax": 22
    },
    {
        "label": "background",
        "xmin": 51,
        "ymin": 245,
        "xmax": 27,
        "ymax": 11
    },
    {
        "label": "background",
        "xmin": 174,
        "ymin": 246,
        "xmax": 10,
        "ymax": 10
    },
    {
        "label": "background",
        "xmin": 123,
        "ymin": 246,
        "xmax": 30,
        "ymax": 10
    },
    {
        "label": "background",
        "xmin": 108,
        "ymin": 116,
        "xmax": 18,
        "ymax": 18
    },
    {
        "label": "background",
        "xmin": 106,
        "ymin": 150,
        "xmax": 150,
        "ymax": 106
    },
    {
        "label": "background",
        "xmin": 106,
        "ymin": 165,
        "xmax": 150,
        "ymax": 91
    },
    {
        "label": "background",
        "xmin": 0,
        "ymin": 119,
        "xmax": 144,
        "ymax": 137
    },
    {
        "label": "background",
        "xmin": 58,
        "ymin": 65,
        "xmax": 80,
        "ymax": 44
    },
    {
        "label": "background",
        "xmin": 40,
        "ymin": 101,
        "xmax": 18,
        "ymax": 10
    },
    {
        "label": "background",
        "xmin": 0,
        "ymin": 63,
        "xmax": 28,
        "ymax": 19
    },
    {
        "label": "background",
        "xmin": 164,
        "ymin": 165,
        "xmax": 14,
        "ymax": 26
    },
    {
        "label": "background",
        "xmin": 40,
        "ymin": 97,
        "xmax": 39,
        "ymax": 14
    },
    {
        "label": "background",
        "xmin": 94,
        "ymin": 87,
        "xmax": 100,
        "ymax": 6
    },
    {
        "label": "background",
        "xmin": 0,
        "ymin": 54,
        "xmax": 28,
        "ymax": 21
    },
    {
        "label": "background",
        "xmin": 89,
        "ymin": 91,
        "xmax": 167,
        "ymax": 112
    },
    {
        "label": "background",
        "xmin": 149,
        "ymin": 213,
        "xmax": 24,
        "ymax": 32
    },
    {
        "label": "background",
        "xmin": 62,
        "ymin": 77,
        "xmax": 23,
        "ymax": 11
    },
    {
        "label": "background",
        "xmin": 187,
        "ymin": 103,
        "xmax": 69,
        "ymax": 62
    },
    {
        "label": "background",
        "xmin": 211,
        "ymin": 189,
        "xmax": 25,
        "ymax": 17
    },
    {
        "label": "background",
        "xmin": 0,
        "ymin": 54,
        "xmax": 256,
        "ymax": 44
    },
    {
        "label": "background",
        "xmin": 84,
        "ymin": 140,
        "xmax": 74,
        "ymax": 40
    },
    {
        "label": "background",
        "xmin": 90,
        "ymin": 61,
        "xmax": 43,
        "ymax": 29
    },
    {
        "label": "background",
        "xmin": 0,
        "ymin": 54,
        "xmax": 30,
        "ymax": 30
    },
    {
        "label": "background",
        "xmin": 228,
        "ymin": 113,
        "xmax": 28,
        "ymax": 67
    },
    {
        "label": "background",
        "xmin": 108,
        "ymin": 149,
        "xmax": 29,
        "ymax": 9
    },
    {
        "label": "background",
        "xmin": 153,
        "ymin": 158,
        "xmax": 29,
        "ymax": 33
    },
    {
        "label": "background",
        "xmin": 112,
        "ymin": 158,
        "xmax": 34,
        "ymax": 19
    },
    {
        "label": "background",
        "xmin": 10,
        "ymin": 74,
        "xmax": 34,
        "ymax": 11
    },
    {
        "label": "background",
        "xmin": 131,
        "ymin": 182,
        "xmax": 14,
        "ymax": 19
    },
    {
        "label": "background",
        "xmin": 143,
        "ymin": 77,
        "xmax": 113,
        "ymax": 76
    },
    {
        "label": "background",
        "xmin": 87,
        "ymin": 199,
        "xmax": 87,
        "ymax": 57
    },
    {
        "label": "background",
        "xmin": 92,
        "ymin": 143,
        "xmax": 66,
        "ymax": 37
    },
    {
        "label": "background",
        "xmin": 0,
        "ymin": 0,
        "xmax": 256,
        "ymax": 91
    },
    {
        "label": "background",
        "xmin": 249,
        "ymin": 114,
        "xmax": 7,
        "ymax": 29
    },
    {
        "label": "background",
        "xmin": 59,
        "ymin": 83,
        "xmax": 63,
        "ymax": 38
    },
    {
        "label": "background",
        "xmin": 249,
        "ymin": 113,
        "xmax": 7,
        "ymax": 30
    },
    {
        "label": "background",
        "xmin": 0,
        "ymin": 74,
        "xmax": 168,
        "ymax": 73
    },
    {
        "label": "background",
        "xmin": 152,
        "ymin": 67,
        "xmax": 104,
        "ymax": 29
    },
    {
        "label": "background",
        "xmin": 76,
        "ymin": 106,
        "xmax": 39,
        "ymax": 15
    },
    {
        "label": "background",
        "xmin": 92,
        "ymin": 199,
        "xmax": 52,
        "ymax": 46
    },
    {
        "label": "background",
        "xmin": 122,
        "ymin": 178,
        "xmax": 18,
        "ymax": 15
    },
    {
        "label": "background",
        "xmin": 25,
        "ymin": 84,
        "xmax": 127,
        "ymax": 22
    },
    {
        "label": "background",
        "xmin": 93,
        "ymin": 157,
        "xmax": 30,
        "ymax": 10
    },
    {
        "label": "background",
        "xmin": 84,
        "ymin": 89,
        "xmax": 68,
        "ymax": 22
    },
    {
        "label": "background",
        "xmin": 95,
        "ymin": 67,
        "xmax": 100,
        "ymax": 25
    },
    {
        "label": "background",
        "xmin": 122,
        "ymin": 134,
        "xmax": 49,
        "ymax": 44
    },
    {
        "label": "background",
        "xmin": 185,
        "ymin": 78,
        "xmax": 71,
        "ymax": 22
    },
    {
        "label": "background",
        "xmin": 0,
        "ymin": 74,
        "xmax": 152,
        "ymax": 77
    },
    {
        "label": "background",
        "xmin": 77,
        "ymin": 157,
        "xmax": 46,
        "ymax": 28
    },
    {
        "label": "background",
        "xmin": 96,
        "ymin": 61,
        "xmax": 96,
        "ymax": 31
    },
    {
        "label": "background",
        "xmin": 217,
        "ymin": 198,
        "xmax": 39,
        "ymax": 32
    },
    {
        "label": "background",
        "xmin": 44,
        "ymin": 75,
        "xmax": 35,
        "ymax": 18
    },
    {
        "label": "background",
        "xmin": 101,
        "ymin": 181,
        "xmax": 31,
        "ymax": 12
    },
    {
        "label": "background",
        "xmin": 115,
        "ymin": 68,
        "xmax": 69,
        "ymax": 24
    },
    {
        "label": "background",
        "xmin": 77,
        "ymin": 157,
        "xmax": 69,
        "ymax": 36
    },
    {
        "label": "background",
        "xmin": 0,
        "ymin": 52,
        "xmax": 154,
        "ymax": 40
    },
    {
        "label": "background",
        "xmin": 87,
        "ymin": 75,
        "xmax": 32,
        "ymax": 17
    },
    {
        "label": "background",
        "xmin": 129,
        "ymin": 91,
        "xmax": 38,
        "ymax": 52
    },
    {
        "label": "background",
        "xmin": 101,
        "ymin": 164,
        "xmax": 44,
        "ymax": 17
    },
    {
        "label": "background",
        "xmin": 102,
        "ymin": 246,
        "xmax": 21,
        "ymax": 10
    },
    {
        "label": "background",
        "xmin": 0,
        "ymin": 138,
        "xmax": 32,
        "ymax": 14
    },
    {
        "label": "background",
        "xmin": 92,
        "ymin": 199,
        "xmax": 38,
        "ymax": 25
    },
    {
        "label": "background",
        "xmin": 102,
        "ymin": 233,
        "xmax": 53,
        "ymax": 23
    },
    {
        "label": "background",
        "xmin": 187,
        "ymin": 103,
        "xmax": 69,
        "ymax": 49
    },
    {
        "label": "background",
        "xmin": 133,
        "ymin": 182,
        "xmax": 10,
        "ymax": 18
    },
    {
        "label": "background",
        "xmin": 0,
        "ymin": 141,
        "xmax": 31,
        "ymax": 11
    },
    {
        "label": "background",
        "xmin": 187,
        "ymin": 82,
        "xmax": 33,
        "ymax": 11
    },
    {
        "label": "background",
        "xmin": 153,
        "ymin": 159,
        "xmax": 18,
        "ymax": 19
    },
    {
        "label": "background",
        "xmin": 90,
        "ymin": 201,
        "xmax": 30,
        "ymax": 25
    },
    {
        "label": "background",
        "xmin": 47,
        "ymin": 68,
        "xmax": 18,
        "ymax": 6
    },
    {
        "label": "background",
        "xmin": 129,
        "ymin": 94,
        "xmax": 27,
        "ymax": 37
    },
    {
        "label": "background",
        "xmin": 217,
        "ymin": 149,
        "xmax": 16,
        "ymax": 20
    },
    {
        "label": "background",
        "xmin": 0,
        "ymin": 52,
        "xmax": 75,
        "ymax": 35
    },
    {
        "label": "background",
        "xmin": 103,
        "ymin": 246,
        "xmax": 50,
        "ymax": 10
    },
    {
        "label": "background",
        "xmin": 0,
        "ymin": 57,
        "xmax": 138,
        "ymax": 52
    },
    {
        "label": "background",
        "xmin": 188,
        "ymin": 109,
        "xmax": 51,
        "ymax": 56
    },
    {
        "label": "background",
        "xmin": 130,
        "ymin": 228,
        "xmax": 46,
        "ymax": 28
    },
    {
        "label": "background",
        "xmin": 183,
        "ymin": 135,
        "xmax": 13,
        "ymax": 18
    },
    {
        "label": "background",
        "xmin": 0,
        "ymin": 57,
        "xmax": 256,
        "ymax": 107
    },
    {
        "label": "background",
        "xmin": 187,
        "ymin": 103,
        "xmax": 69,
        "ymax": 65
    },
    {
        "label": "background",
        "xmin": 123,
        "ymin": 146,
        "xmax": 31,
        "ymax": 24
    },
    {
        "label": "background",
        "xmin": 0,
        "ymin": 116,
        "xmax": 111,
        "ymax": 130
    },
    {
        "label": "background",
        "xmin": 190,
        "ymin": 147,
        "xmax": 21,
        "ymax": 16
    },
    {
        "label": "background",
        "xmin": 126,
        "ymin": 165,
        "xmax": 130,
        "ymax": 91
    },
    {
        "label": "background",
        "xmin": 92,
        "ymin": 105,
        "xmax": 33,
        "ymax": 28
    },
    {
        "label": "background",
        "xmin": 182,
        "ymin": 172,
        "xmax": 74,
        "ymax": 57
    },
    {
        "label": "background",
        "xmin": 187,
        "ymin": 103,
        "xmax": 69,
        "ymax": 76
    },
    {
        "label": "background",
        "xmin": 159,
        "ymin": 165,
        "xmax": 18,
        "ymax": 24
    },
    {
        "label": "background",
        "xmin": 205,
        "ymin": 188,
        "xmax": 51,
        "ymax": 23
    },
    {
        "label": "background",
        "xmin": 94,
        "ymin": 83,
        "xmax": 144,
        "ymax": 25
    },
    {
        "label": "background",
        "xmin": 87,
        "ymin": 146,
        "xmax": 169,
        "ymax": 110
    },
    {
        "label": "background",
        "xmin": 99,
        "ymin": 163,
        "xmax": 53,
        "ymax": 26
    },
    {
        "label": "background",
        "xmin": 225,
        "ymin": 199,
        "xmax": 31,
        "ymax": 31
    },
    {
        "label": "background",
        "xmin": 41,
        "ymin": 84,
        "xmax": 49,
        "ymax": 20
    },
    {
        "label": "background",
        "xmin": 155,
        "ymin": 103,
        "xmax": 5,
        "ymax": 34
    },
    {
        "label": "background",
        "xmin": 184,
        "ymin": 83,
        "xmax": 54,
        "ymax": 14
    },
    {
        "label": "background",
        "xmin": 92,
        "ymin": 144,
        "xmax": 29,
        "ymax": 6
    },
    {
        "label": "background",
        "xmin": 182,
        "ymin": 172,
        "xmax": 55,
        "ymax": 47
    },
    {
        "label": "background",
        "xmin": 84,
        "ymin": 140,
        "xmax": 62,
        "ymax": 37
    },
    {
        "label": "background",
        "xmin": 201,
        "ymin": 109,
        "xmax": 5,
        "ymax": 27
    },
    {
        "label": "background",
        "xmin": 81,
        "ymin": 140,
        "xmax": 175,
        "ymax": 116
    },
    {
        "label": "background",
        "xmin": 111,
        "ymin": 158,
        "xmax": 36,
        "ymax": 19
    },
    {
        "label": "background",
        "xmin": 68,
        "ymin": 65,
        "xmax": 61,
        "ymax": 56
    },
    {
        "label": "background",
        "xmin": 0,
        "ymin": 96,
        "xmax": 131,
        "ymax": 160
    },
    {
        "label": "background",
        "xmin": 46,
        "ymin": 68,
        "xmax": 21,
        "ymax": 6
    },
    {
        "label": "background",
        "xmin": 92,
        "ymin": 165,
        "xmax": 164,
        "ymax": 91
    },
    {
        "label": "background",
        "xmin": 131,
        "ymin": 181,
        "xmax": 14,
        "ymax": 20
    },
    {
        "label": "background",
        "xmin": 213,
        "ymin": 85,
        "xmax": 25,
        "ymax": 15
    },
    {
        "label": "background",
        "xmin": 122,
        "ymin": 134,
        "xmax": 57,
        "ymax": 57
    },
    {
        "label": "background",
        "xmin": 221,
        "ymin": 190,
        "xmax": 35,
        "ymax": 21
    },
    {
        "label": "background",
        "xmin": 81,
        "ymin": 139,
        "xmax": 41,
        "ymax": 11
    },
    {
        "label": "background",
        "xmin": 81,
        "ymin": 140,
        "xmax": 77,
        "ymax": 61
    },
    {
        "label": "background",
        "xmin": 92,
        "ymin": 146,
        "xmax": 46,
        "ymax": 17
    },
    {
        "label": "background",
        "xmin": 0,
        "ymin": 93,
        "xmax": 256,
        "ymax": 163
    },
    {
        "label": "background",
        "xmin": 41,
        "ymin": 124,
        "xmax": 26,
        "ymax": 14
    },
    {
        "label": "background",
        "xmin": 93,
        "ymin": 200,
        "xmax": 36,
        "ymax": 23
    },
    {
        "label": "background",
        "xmin": 152,
        "ymin": 66,
        "xmax": 104,
        "ymax": 32
    },
    {
        "label": "background",
        "xmin": 230,
        "ymin": 172,
        "xmax": 26,
        "ymax": 9
    },
    {
        "label": "background",
        "xmin": 192,
        "ymin": 184,
        "xmax": 64,
        "ymax": 27
    },
    {
        "label": "background",
        "xmin": 89,
        "ymin": 61,
        "xmax": 167,
        "ymax": 34
    },
    {
        "label": "background",
        "xmin": 152,
        "ymin": 77,
        "xmax": 104,
        "ymax": 16
    },
    {
        "label": "background",
        "xmin": 108,
        "ymin": 146,
        "xmax": 46,
        "ymax": 24
    },
    {
        "label": "background",
        "xmin": 0,
        "ymin": 52,
        "xmax": 119,
        "ymax": 40
    },
    {
        "label": "background",
        "xmin": 99,
        "ymin": 179,
        "xmax": 46,
        "ymax": 22
    },
    {
        "label": "background",
        "xmin": 87,
        "ymin": 199,
        "xmax": 46,
        "ymax": 27
    },
    {
        "label": "background",
        "xmin": 0,
        "ymin": 0,
        "xmax": 256,
        "ymax": 86
    },
    {
        "label": "background",
        "xmin": 175,
        "ymin": 68,
        "xmax": 20,
        "ymax": 6
    },
    {
        "label": "background",
        "xmin": 102,
        "ymin": 232,
        "xmax": 65,
        "ymax": 24
    },
    {
        "label": "background",
        "xmin": 234,
        "ymin": 197,
        "xmax": 22,
        "ymax": 11
    },
    {
        "label": "background",
        "xmin": 182,
        "ymin": 173,
        "xmax": 26,
        "ymax": 18
    },
    {
        "label": "background",
        "xmin": 185,
        "ymin": 83,
        "xmax": 71,
        "ymax": 17
    },
    {
        "label": "background",
        "xmin": 178,
        "ymin": 170,
        "xmax": 34,
        "ymax": 22
    },
    {
        "label": "background",
        "xmin": 118,
        "ymin": 160,
        "xmax": 138,
        "ymax": 96
    },
    {
        "label": "background",
        "xmin": 97,
        "ymin": 182,
        "xmax": 36,
        "ymax": 23
    },
    {
        "label": "background",
        "xmin": 164,
        "ymin": 246,
        "xmax": 20,
        "ymax": 10
    },
    {
        "label": "background",
        "xmin": 245,
        "ymin": 66,
        "xmax": 11,
        "ymax": 12
    },
    {
        "label": "background",
        "xmin": 102,
        "ymin": 172,
        "xmax": 44,
        "ymax": 20
    },
    {
        "label": "background",
        "xmin": 168,
        "ymin": 168,
        "xmax": 9,
        "ymax": 21
    },
    {
        "label": "background",
        "xmin": 109,
        "ymin": 232,
        "xmax": 58,
        "ymax": 24
    },
    {
        "label": "background",
        "xmin": 59,
        "ymin": 83,
        "xmax": 63,
        "ymax": 36
    },
    {
        "label": "background",
        "xmin": 166,
        "ymin": 101,
        "xmax": 17,
        "ymax": 51
    },
    {
        "label": "background",
        "xmin": 102,
        "ymin": 231,
        "xmax": 82,
        "ymax": 25
    },
    {
        "label": "background",
        "xmin": 101,
        "ymin": 232,
        "xmax": 66,
        "ymax": 24
    },
    {
        "label": "background",
        "xmin": 163,
        "ymin": 171,
        "xmax": 29,
        "ymax": 22
    },
    {
        "label": "background",
        "xmin": 44,
        "ymin": 65,
        "xmax": 81,
        "ymax": 28
    },
    {
        "label": "background",
        "xmin": 0,
        "ymin": 63,
        "xmax": 126,
        "ymax": 71
    },
    {
        "label": "background",
        "xmin": 183,
        "ymin": 103,
        "xmax": 73,
        "ymax": 77
    },
    {
        "label": "background",
        "xmin": 98,
        "ymin": 180,
        "xmax": 33,
        "ymax": 13
    },
    {
        "label": "background",
        "xmin": 92,
        "ymin": 143,
        "xmax": 55,
        "ymax": 34
    },
    {
        "label": "background",
        "xmin": 185,
        "ymin": 83,
        "xmax": 71,
        "ymax": 85
    },
    {
        "label": "background",
        "xmin": 153,
        "ymin": 158,
        "xmax": 103,
        "ymax": 53
    },
    {
        "label": "background",
        "xmin": 217,
        "ymin": 113,
        "xmax": 39,
        "ymax": 67
    },
    {
        "label": "background",
        "xmin": 83,
        "ymin": 107,
        "xmax": 49,
        "ymax": 40
    },
    {
        "label": "background",
        "xmin": 70,
        "ymin": 65,
        "xmax": 55,
        "ymax": 25
    },
    {
        "label": "background",
        "xmin": 171,
        "ymin": 159,
        "xmax": 23,
        "ymax": 32
    },
    {
        "label": "background",
        "xmin": 92,
        "ymin": 157,
        "xmax": 55,
        "ymax": 24
    },
    {
        "label": "background",
        "xmin": 117,
        "ymin": 65,
        "xmax": 76,
        "ymax": 24
    },
    {
        "label": "background",
        "xmin": 57,
        "ymin": 232,
        "xmax": 25,
        "ymax": 14
    },
    {
        "label": "background",
        "xmin": 35,
        "ymin": 84,
        "xmax": 28,
        "ymax": 8
    },
    {
        "label": "background",
        "xmin": 208,
        "ymin": 187,
        "xmax": 43,
        "ymax": 17
    },
    {
        "label": "background",
        "xmin": 0,
        "ymin": 54,
        "xmax": 67,
        "ymax": 31
    },
    {
        "label": "background",
        "xmin": 0,
        "ymin": 64,
        "xmax": 256,
        "ymax": 147
    },
    {
        "label": "background",
        "xmin": 90,
        "ymin": 150,
        "xmax": 63,
        "ymax": 81
    },
    {
        "label": "background",
        "xmin": 109,
        "ymin": 232,
        "xmax": 45,
        "ymax": 24
    },
    {
        "label": "background",
        "xmin": 59,
        "ymin": 65,
        "xmax": 67,
        "ymax": 69
    },
    {
        "label": "background",
        "xmin": 103,
        "ymin": 247,
        "xmax": 20,
        "ymax": 9
    },
    {
        "label": "background",
        "xmin": 0,
        "ymin": 0,
        "xmax": 256,
        "ymax": 89
    },
    {
        "label": "background",
        "xmin": 10,
        "ymin": 72,
        "xmax": 37,
        "ymax": 11
    },
    {
        "label": "background",
        "xmin": 0,
        "ymin": 74,
        "xmax": 256,
        "ymax": 125
    },
    {
        "label": "background",
        "xmin": 101,
        "ymin": 232,
        "xmax": 53,
        "ymax": 24
    },
    {
        "label": "background",
        "xmin": 95,
        "ymin": 65,
        "xmax": 161,
        "ymax": 30
    },
    {
        "label": "background",
        "xmin": 149,
        "ymin": 212,
        "xmax": 35,
        "ymax": 44
    },
    {
        "label": "background",
        "xmin": 92,
        "ymin": 157,
        "xmax": 37,
        "ymax": 10
    },
    {
        "label": "background",
        "xmin": 92,
        "ymin": 233,
        "xmax": 21,
        "ymax": 18
    },
    {
        "label": "background",
        "xmin": 103,
        "ymin": 231,
        "xmax": 81,
        "ymax": 25
    },
    {
        "label": "background",
        "xmin": 0,
        "ymin": 0,
        "xmax": 256,
        "ymax": 256
    },
    {
        "label": "background",
        "xmin": 0,
        "ymin": 70,
        "xmax": 122,
        "ymax": 49
    },
    {
        "label": "background",
        "xmin": 26,
        "ymin": 84,
        "xmax": 40,
        "ymax": 10
    },
    {
        "label": "background",
        "xmin": 202,
        "ymin": 84,
        "xmax": 54,
        "ymax": 11
    },
    {
        "label": "background",
        "xmin": 76,
        "ymin": 106,
        "xmax": 50,
        "ymax": 28
    },
    {
        "label": "background",
        "xmin": 108,
        "ymin": 148,
        "xmax": 39,
        "ymax": 29
    },
    {
        "label": "background",
        "xmin": 114,
        "ymin": 162,
        "xmax": 33,
        "ymax": 15
    },
    {
        "label": "background",
        "xmin": 166,
        "ymin": 87,
        "xmax": 90,
        "ymax": 66
    },
    {
        "label": "background",
        "xmin": 0,
        "ymin": 128,
        "xmax": 62,
        "ymax": 24
    },
    {
        "label": "background",
        "xmin": 157,
        "ymin": 87,
        "xmax": 99,
        "ymax": 65
    },
    {
        "label": "background",
        "xmin": 0,
        "ymin": 132,
        "xmax": 47,
        "ymax": 20
    },
    {
        "label": "background",
        "xmin": 26,
        "ymin": 64,
        "xmax": 126,
        "ymax": 61
    },
    {
        "label": "background",
        "xmin": 117,
        "ymin": 65,
        "xmax": 78,
        "ymax": 24
    },
    {
        "label": "background",
        "xmin": 90,
        "ymin": 143,
        "xmax": 63,
        "ymax": 88
    },
    {
        "label": "background",
        "xmin": 124,
        "ymin": 91,
        "xmax": 59,
        "ymax": 61
    },
    {
        "label": "background",
        "xmin": 178,
        "ymin": 170,
        "xmax": 78,
        "ymax": 41
    },
    {
        "label": "background",
        "xmin": 0,
        "ymin": 74,
        "xmax": 169,
        "ymax": 78
    },
    {
        "label": "background",
        "xmin": 93,
        "ymin": 200,
        "xmax": 59,
        "ymax": 31
    },
    {
        "label": "background",
        "xmin": 0,
        "ymin": 63,
        "xmax": 256,
        "ymax": 148
    },
    {
        "label": "background",
        "xmin": 122,
        "ymin": 134,
        "xmax": 41,
        "ymax": 34
    },
    {
        "label": "background",
        "xmin": 115,
        "ymin": 61,
        "xmax": 77,
        "ymax": 31
    },
    {
        "label": "background",
        "xmin": 0,
        "ymin": 70,
        "xmax": 122,
        "ymax": 56
    },
    {
        "label": "background",
        "xmin": 0,
        "ymin": 0,
        "xmax": 256,
        "ymax": 109
    },
    {
        "label": "background",
        "xmin": 97,
        "ymin": 172,
        "xmax": 49,
        "ymax": 33
    },
    {
        "label": "background",
        "xmin": 108,
        "ymin": 149,
        "xmax": 38,
        "ymax": 28
    },
    {
        "label": "background",
        "xmin": 92,
        "ymin": 157,
        "xmax": 55,
        "ymax": 36
    },
    {
        "label": "background",
        "xmin": 153,
        "ymin": 158,
        "xmax": 55,
        "ymax": 33
    },
    {
        "label": "background",
        "xmin": 0,
        "ymin": 57,
        "xmax": 104,
        "ymax": 29
    },
    {
        "label": "background",
        "xmin": 0,
        "ymin": 63,
        "xmax": 131,
        "ymax": 193
    },
    {
        "label": "background",
        "xmin": 90,
        "ymin": 165,
        "xmax": 166,
        "ymax": 91
    },
    {
        "label": "background",
        "xmin": 62,
        "ymin": 65,
        "xmax": 67,
        "ymax": 69
    },
    {
        "label": "background",
        "xmin": 0,
        "ymin": 116,
        "xmax": 126,
        "ymax": 140
    },
    {
        "label": "background",
        "xmin": 0,
        "ymin": 54,
        "xmax": 47,
        "ymax": 29
    },
    {
        "label": "background",
        "xmin": 187,
        "ymin": 91,
        "xmax": 69,
        "ymax": 12
    },
    {
        "label": "background",
        "xmin": 87,
        "ymin": 199,
        "xmax": 53,
        "ymax": 52
    },
    {
        "label": "background",
        "xmin": 90,
        "ymin": 61,
        "xmax": 94,
        "ymax": 31
    },
    {
        "label": "background",
        "xmin": 122,
        "ymin": 134,
        "xmax": 87,
        "ymax": 59
    },
    {
        "label": "background",
        "xmin": 84,
        "ymin": 140,
        "xmax": 53,
        "ymax": 18
    },
    {
        "label": "background",
        "xmin": 0,
        "ymin": 77,
        "xmax": 256,
        "ymax": 179
    },
    {
        "label": "background",
        "xmin": 93,
        "ymin": 148,
        "xmax": 60,
        "ymax": 57
    },
    {
        "label": "background",
        "xmin": 166,
        "ymin": 87,
        "xmax": 90,
        "ymax": 92
    },
    {
        "label": "background",
        "xmin": 0,
        "ymin": 70,
        "xmax": 77,
        "ymax": 35
    },
    {
        "label": "background",
        "xmin": 0,
        "ymin": 52,
        "xmax": 117,
        "ymax": 37
    },
    {
        "label": "background",
        "xmin": 92,
        "ymin": 221,
        "xmax": 48,
        "ymax": 30
    },
    {
        "label": "background",
        "xmin": 99,
        "ymin": 165,
        "xmax": 157,
        "ymax": 91
    },
    {
        "label": "background",
        "xmin": 103,
        "ymin": 233,
        "xmax": 64,
        "ymax": 23
    },
    {
        "label": "background",
        "xmin": 0,
        "ymin": 63,
        "xmax": 256,
        "ymax": 193
    },
    {
        "label": "background",
        "xmin": 0,
        "ymin": 0,
        "xmax": 256,
        "ymax": 96
    },
    {
        "label": "background",
        "xmin": 0,
        "ymin": 54,
        "xmax": 256,
        "ymax": 46
    },
    {
        "label": "background",
        "xmin": 129,
        "ymin": 87,
        "xmax": 127,
        "ymax": 65
    },
    {
        "label": "background",
        "xmin": 98,
        "ymin": 172,
        "xmax": 48,
        "ymax": 21
    },
    {
        "label": "background",
        "xmin": 83,
        "ymin": 87,
        "xmax": 173,
        "ymax": 118
    },
    {
        "label": "background",
        "xmin": 112,
        "ymin": 87,
        "xmax": 144,
        "ymax": 111
    },
    {
        "label": "background",
        "xmin": 90,
        "ymin": 61,
        "xmax": 102,
        "ymax": 31
    },
    {
        "label": "background",
        "xmin": 188,
        "ymin": 109,
        "xmax": 68,
        "ymax": 71
    },
    {
        "label": "background",
        "xmin": 182,
        "ymin": 173,
        "xmax": 74,
        "ymax": 38
    },
    {
        "label": "background",
        "xmin": 122,
        "ymin": 134,
        "xmax": 87,
        "ymax": 57
    },
    {
        "label": "background",
        "xmin": 87,
        "ymin": 160,
        "xmax": 169,
        "ymax": 96
    },
    {
        "label": "background",
        "xmin": 101,
        "ymin": 212,
        "xmax": 86,
        "ymax": 44
    },
    {
        "label": "background",
        "xmin": 0,
        "ymin": 64,
        "xmax": 256,
        "ymax": 134
    },
    {
        "label": "background",
        "xmin": 41,
        "ymin": 84,
        "xmax": 126,
        "ymax": 59
    },
    {
        "label": "background",
        "xmin": 174,
        "ymin": 147,
        "xmax": 37,
        "ymax": 16
    },
    {
        "label": "background",
        "xmin": 157,
        "ymin": 65,
        "xmax": 99,
        "ymax": 30
    },
    {
        "label": "background",
        "xmin": 0,
        "ymin": 64,
        "xmax": 152,
        "ymax": 88
    },
    {
        "label": "background",
        "xmin": 62,
        "ymin": 65,
        "xmax": 67,
        "ymax": 56
    },
    {
        "label": "background",
        "xmin": 124,
        "ymin": 91,
        "xmax": 132,
        "ymax": 73
    },
    {
        "label": "background",
        "xmin": 166,
        "ymin": 87,
        "xmax": 90,
        "ymax": 79
    },
    {
        "label": "background",
        "xmin": 124,
        "ymin": 91,
        "xmax": 59,
        "ymax": 54
    },
    {
        "label": "background",
        "xmin": 112,
        "ymin": 67,
        "xmax": 83,
        "ymax": 22
    },
    {
        "label": "background",
        "xmin": 84,
        "ymin": 89,
        "xmax": 85,
        "ymax": 54
    },
    {
        "label": "background",
        "xmin": 101,
        "ymin": 164,
        "xmax": 44,
        "ymax": 29
    },
    {
        "label": "background",
        "xmin": 0,
        "ymin": 74,
        "xmax": 167,
        "ymax": 78
    },
    {
        "label": "background",
        "xmin": 99,
        "ymin": 163,
        "xmax": 53,
        "ymax": 30
    },
    {
        "label": "background",
        "xmin": 123,
        "ymin": 233,
        "xmax": 44,
        "ymax": 23
    },
    {
        "label": "background",
        "xmin": 152,
        "ymin": 212,
        "xmax": 32,
        "ymax": 44
    },
    {
        "label": "background",
        "xmin": 68,
        "ymin": 65,
        "xmax": 61,
        "ymax": 69
    },
    {
        "label": "background",
        "xmin": 26,
        "ymin": 64,
        "xmax": 126,
        "ymax": 47
    },
    {
        "label": "background",
        "xmin": 60,
        "ymin": 146,
        "xmax": 94,
        "ymax": 49
    },
    {
        "label": "background",
        "xmin": 60,
        "ymin": 156,
        "xmax": 86,
        "ymax": 39
    },
    {
        "label": "background",
        "xmin": 0,
        "ymin": 74,
        "xmax": 169,
        "ymax": 73
    },
    {
        "label": "background",
        "xmin": 0,
        "ymin": 74,
        "xmax": 168,
        "ymax": 78
    },
    {
        "label": "background",
        "xmin": 0,
        "ymin": 74,
        "xmax": 256,
        "ymax": 182
    },
    {
        "label": "background",
        "xmin": 0,
        "ymin": 52,
        "xmax": 256,
        "ymax": 44
    },
    {
        "label": "background",
        "xmin": 119,
        "ymin": 87,
        "xmax": 137,
        "ymax": 79
    },
    {
        "label": "background",
        "xmin": 60,
        "ymin": 156,
        "xmax": 63,
        "ymax": 39
    },
    {
        "label": "background",
        "xmin": 0,
        "ymin": 54,
        "xmax": 125,
        "ymax": 39
    },
    {
        "label": "background",
        "xmin": 183,
        "ymin": 103,
        "xmax": 73,
        "ymax": 62
    },
    {
        "label": "background",
        "xmin": 41,
        "ymin": 84,
        "xmax": 111,
        "ymax": 35
    },
    {
        "label": "background",
        "xmin": 81,
        "ymin": 126,
        "xmax": 175,
        "ymax": 130
    },
    {
        "label": "background",
        "xmin": 0,
        "ymin": 57,
        "xmax": 129,
        "ymax": 77
    },
    {
        "label": "background",
        "xmin": 83,
        "ymin": 107,
        "xmax": 173,
        "ymax": 149
    },
    {
        "label": "background",
        "xmin": 171,
        "ymin": 159,
        "xmax": 38,
        "ymax": 32
    },
    {
        "label": "background",
        "xmin": 96,
        "ymin": 68,
        "xmax": 88,
        "ymax": 24
    },
    {
        "label": "background",
        "xmin": 118,
        "ymin": 146,
        "xmax": 138,
        "ymax": 110
    },
    {
        "label": "background",
        "xmin": 81,
        "ymin": 140,
        "xmax": 77,
        "ymax": 33
    },
    {
        "label": "background",
        "xmin": 60,
        "ymin": 156,
        "xmax": 80,
        "ymax": 39
    },
    {
        "label": "background",
        "xmin": 90,
        "ymin": 172,
        "xmax": 62,
        "ymax": 59
    },
    {
        "label": "background",
        "xmin": 61,
        "ymin": 89,
        "xmax": 108,
        "ymax": 54
    },
    {
        "label": "background",
        "xmin": 89,
        "ymin": 83,
        "xmax": 167,
        "ymax": 120
    },
    {
        "label": "background",
        "xmin": 0,
        "ymin": 52,
        "xmax": 256,
        "ymax": 43
    },
    {
        "label": "background",
        "xmin": 94,
        "ymin": 77,
        "xmax": 162,
        "ymax": 20
    },
    {
        "label": "background",
        "xmin": 185,
        "ymin": 83,
        "xmax": 71,
        "ymax": 20
    },
    {
        "label": "background",
        "xmin": 0,
        "ymin": 57,
        "xmax": 104,
        "ymax": 61
    },
    {
        "label": "background",
        "xmin": 0,
        "ymin": 74,
        "xmax": 256,
        "ymax": 137
    },
    {
        "label": "background",
        "xmin": 0,
        "ymin": 54,
        "xmax": 119,
        "ymax": 38
    },
    {
        "label": "background",
        "xmin": 0,
        "ymin": 52,
        "xmax": 179,
        "ymax": 40
    },
    {
        "label": "background",
        "xmin": 124,
        "ymin": 83,
        "xmax": 132,
        "ymax": 85
    },
    {
        "label": "background",
        "xmin": 182,
        "ymin": 172,
        "xmax": 74,
        "ymax": 58
    },
    {
        "label": "background",
        "xmin": 90,
        "ymin": 143,
        "xmax": 63,
        "ymax": 103
    },
    {
        "label": "background",
        "xmin": 0,
        "ymin": 54,
        "xmax": 47,
        "ymax": 31
    },
    {
        "label": "background",
        "xmin": 102,
        "ymin": 222,
        "xmax": 82,
        "ymax": 34
    },
    {
        "label": "background",
        "xmin": 62,
        "ymin": 65,
        "xmax": 57,
        "ymax": 27
    },
    {
        "label": "background",
        "xmin": 211,
        "ymin": 189,
        "xmax": 45,
        "ymax": 40
    },
    {
        "label": "background",
        "xmin": 84,
        "ymin": 140,
        "xmax": 68,
        "ymax": 53
    },
    {
        "label": "background",
        "xmin": 77,
        "ymin": 157,
        "xmax": 69,
        "ymax": 28
    },
    {
        "label": "background",
        "xmin": 84,
        "ymin": 140,
        "xmax": 68,
        "ymax": 49
    },
    {
        "label": "background",
        "xmin": 101,
        "ymin": 232,
        "xmax": 73,
        "ymax": 24
    },
    {
        "label": "background",
        "xmin": 93,
        "ymin": 200,
        "xmax": 91,
        "ymax": 56
    },
    {
        "label": "background",
        "xmin": 60,
        "ymin": 149,
        "xmax": 86,
        "ymax": 46
    },
    {
        "label": "background",
        "xmin": 103,
        "ymin": 213,
        "xmax": 71,
        "ymax": 43
    },
    {
        "label": "background",
        "xmin": 63,
        "ymin": 53,
        "xmax": 116,
        "ymax": 39
    },
    {
        "label": "background",
        "xmin": 94,
        "ymin": 77,
        "xmax": 162,
        "ymax": 87
    },
    {
        "label": "background",
        "xmin": 102,
        "ymin": 232,
        "xmax": 82,
        "ymax": 24
    },
    {
        "label": "background",
        "xmin": 93,
        "ymin": 148,
        "xmax": 54,
        "ymax": 29
    },
    {
        "label": "background",
        "xmin": 0,
        "ymin": 57,
        "xmax": 104,
        "ymax": 34
    },
    {
        "label": "background",
        "xmin": 117,
        "ymin": 65,
        "xmax": 139,
        "ymax": 31
    },
    {
        "label": "background",
        "xmin": 0,
        "ymin": 0,
        "xmax": 256,
        "ymax": 164
    },
    {
        "label": "background",
        "xmin": 90,
        "ymin": 172,
        "xmax": 56,
        "ymax": 54
    },
    {
        "label": "background",
        "xmin": 0,
        "ymin": 54,
        "xmax": 256,
        "ymax": 80
    },
    {
        "label": "background",
        "xmin": 0,
        "ymin": 54,
        "xmax": 102,
        "ymax": 34
    },
    {
        "label": "background",
        "xmin": 84,
        "ymin": 126,
        "xmax": 172,
        "ymax": 103
    },
    {
        "label": "background",
        "xmin": 0,
        "ymin": 0,
        "xmax": 256,
        "ymax": 153
    },
    {
        "label": "background",
        "xmin": 182,
        "ymin": 172,
        "xmax": 74,
        "ymax": 47
    },
    {
        "label": "background",
        "xmin": 153,
        "ymin": 158,
        "xmax": 103,
        "ymax": 71
    },
    {
        "label": "background",
        "xmin": 0,
        "ymin": 0,
        "xmax": 256,
        "ymax": 134
    },
    {
        "label": "background",
        "xmin": 0,
        "ymin": 119,
        "xmax": 256,
        "ymax": 137
    },
    {
        "label": "background",
        "xmin": 103,
        "ymin": 213,
        "xmax": 70,
        "ymax": 43
    },
    {
        "label": "background",
        "xmin": 0,
        "ymin": 0,
        "xmax": 256,
        "ymax": 100
    },
    {
        "label": "background",
        "xmin": 90,
        "ymin": 61,
        "xmax": 166,
        "ymax": 37
    },
    {
        "label": "background",
        "xmin": 0,
        "ymin": 74,
        "xmax": 167,
        "ymax": 77
    },
    {
        "label": "background",
        "xmin": 91,
        "ymin": 143,
        "xmax": 67,
        "ymax": 50
    },
    {
        "label": "background",
        "xmin": 102,
        "ymin": 212,
        "xmax": 82,
        "ymax": 44
    },
    {
        "label": "background",
        "xmin": 174,
        "ymin": 103,
        "xmax": 82,
        "ymax": 77
    },
    {
        "label": "background",
        "xmin": 124,
        "ymin": 91,
        "xmax": 68,
        "ymax": 61
    },
    {
        "label": "background",
        "xmin": 0,
        "ymin": 74,
        "xmax": 110,
        "ymax": 78
    },
    {
        "label": "background",
        "xmin": 0,
        "ymin": 54,
        "xmax": 79,
        "ymax": 72
    },
    {
        "label": "background",
        "xmin": 102,
        "ymin": 232,
        "xmax": 72,
        "ymax": 24
    },
    {
        "label": "background",
        "xmin": 94,
        "ymin": 77,
        "xmax": 162,
        "ymax": 31
    },
    {
        "label": "background",
        "xmin": 59,
        "ymin": 65,
        "xmax": 66,
        "ymax": 56
    },
    {
        "label": "background",
        "xmin": 90,
        "ymin": 200,
        "xmax": 94,
        "ymax": 56
    },
    {
        "label": "background",
        "xmin": 0,
        "ymin": 0,
        "xmax": 256,
        "ymax": 98
    },
    {
        "label": "background",
        "xmin": 81,
        "ymin": 126,
        "xmax": 77,
        "ymax": 75
    },
    {
        "label": "background",
        "xmin": 0,
        "ymin": 54,
        "xmax": 256,
        "ymax": 41
    },
    {
        "label": "background",
        "xmin": 87,
        "ymin": 199,
        "xmax": 84,
        "ymax": 57
    },
    {
        "label": "background",
        "xmin": 157,
        "ymin": 87,
        "xmax": 99,
        "ymax": 93
    },
    {
        "label": "background",
        "xmin": 103,
        "ymin": 212,
        "xmax": 84,
        "ymax": 44
    },
    {
        "label": "background",
        "xmin": 0,
        "ymin": 83,
        "xmax": 256,
        "ymax": 173
    },
    {
        "label": "background",
        "xmin": 0,
        "ymin": 63,
        "xmax": 122,
        "ymax": 63
    },
    {
        "label": "background",
        "xmin": 84,
        "ymin": 140,
        "xmax": 172,
        "ymax": 116
    },
    {
        "label": "background",
        "xmin": 0,
        "ymin": 57,
        "xmax": 256,
        "ymax": 199
    },
    {
        "label": "background",
        "xmin": 0,
        "ymin": 74,
        "xmax": 167,
        "ymax": 182
    },
    {
        "label": "background",
        "xmin": 83,
        "ymin": 107,
        "xmax": 126,
        "ymax": 98
    },
    {
        "label": "background",
        "xmin": 83,
        "ymin": 107,
        "xmax": 70,
        "ymax": 98
    },
    {
        "label": "background",
        "xmin": 83,
        "ymin": 107,
        "xmax": 70,
        "ymax": 139
    },
    {
        "label": "background",
        "xmin": 92,
        "ymin": 143,
        "xmax": 61,
        "ymax": 62
    },
    {
        "label": "background",
        "xmin": 81,
        "ymin": 126,
        "xmax": 175,
        "ymax": 85
    },
    {
        "label": "background",
        "xmin": 0,
        "ymin": 54,
        "xmax": 126,
        "ymax": 80
    },
    {
        "label": "background",
        "xmin": 60,
        "ymin": 83,
        "xmax": 196,
        "ymax": 173
    },
    {
        "label": "background",
        "xmin": 84,
        "ymin": 126,
        "xmax": 172,
        "ymax": 130
    },
    {
        "label": "background",
        "xmin": 83,
        "ymin": 87,
        "xmax": 173,
        "ymax": 169
    },
    {
        "label": "background",
        "xmin": 0,
        "ymin": 97,
        "xmax": 256,
        "ymax": 159
    }
]